{"name":"surf_crzyfrog_reloaded_fix","lightmapUrl":"https://raw.githubusercontent.com/RSCSurf/SurfMaps1/main/maps/surf_crzyfrog_reloaded_fix/lightmap.json?v=2048-99ae","leafPages":[{"first":0,"count":4295,"url":"https://raw.githubusercontent.com/RSCSurf/SurfMaps1/main/maps/surf_crzyfrog_reloaded_fix/geom/leafpage0.json?v=2048-99ae"}],"dispPages":[{"first":0,"count":0,"url":"https://raw.githubusercontent.com/RSCSurf/SurfMaps1/main/maps/surf_crzyfrog_reloaded_fix/geom/disppage0.json?v=2048-99ae"}],"materialPages":[{"first":0,"count":61,"url":"https://raw.githubusercontent.com/RSCSurf/SurfMaps1/main/maps/surf_crzyfrog_reloaded_fix/materials/matpage0.json?v=2048-99ae"}],"brushModelPages":[{"first":0,"count":1,"url":"https://raw.githubusercontent.com/RSCSurf/SurfMaps1/main/maps/surf_crzyfrog_reloaded_fix/geom/bsppage0.json?v=2048-99ae"},{"first":1,"count":70,"url":"https://raw.githubusercontent.com/RSCSurf/SurfMaps1/main/maps/surf_crzyfrog_reloaded_fix/geom/bsppage1.json?v=2048-99ae"}],"studioModelPages":[{"first":0,"count":1,"url":"https://raw.githubusercontent.com/RSCSurf/SurfMaps1/main/maps/surf_crzyfrog_reloaded_fix/geom/mdlpage0.json?v=2048-99ae"}],"vertLightingPages":[{"first":0,"count":2,"url":"https://raw.githubusercontent.com/RSCSurf/SurfMaps1/main/maps/surf_crzyfrog_reloaded_fix/geom/vhvpage0.json?v=2048-99ae"}],"visPages":[{"first":0,"count":1021,"url":"https://raw.githubusercontent.com/RSCSurf/SurfMaps1/main/maps/surf_crzyfrog_reloaded_fix/geom/vispage0.json?v=2048-99ae"}],"ambientPages":[{"first":0,"count":4096,"url":"https://raw.githubusercontent.com/RSCSurf/SurfMaps1/main/maps/surf_crzyfrog_reloaded_fix/geom/ambientpage0.json?v=2048-99ae"},{"first":4096,"count":199,"url":"https://raw.githubusercontent.com/RSCSurf/SurfMaps1/main/maps/surf_crzyfrog_reloaded_fix/geom/ambientpage1.json?v=2048-99ae"}],"entities":[{"skyMaterial":{"shader":"SourceUtils.Shaders.Sky","properties":[{"name":"cullFace","type":1,"value":false},{"name":"facePosX","type":4,"value":"https://raw.githubusercontent.com/RSCSurf/SurfMaps1/main/maps/surf_crzyfrog_reloaded_fix/materials/skybox/mpa15_2rt.vtf.json?v=2048-99ae"},{"name":"faceNegX","type":4,"value":"https://raw.githubusercontent.com/RSCSurf/SurfMaps1/main/maps/surf_crzyfrog_reloaded_fix/materials/skybox/mpa15_2lf.vtf.json?v=2048-99ae"},{"name":"facePosY","type":4,"value":"https://raw.githubusercontent.com/RSCSurf/SurfMaps1/main/maps/surf_crzyfrog_reloaded_fix/materials/skybox/mpa15_2bk.vtf.json?v=2048-99ae"},{"name":"faceNegY","type":4,"value":"https://raw.githubusercontent.com/RSCSurf/SurfMaps1/main/maps/surf_crzyfrog_reloaded_fix/materials/skybox/mpa15_2ft.vtf.json?v=2048-99ae"},{"name":"facePosZ","type":4,"value":"https://raw.githubusercontent.com/RSCSurf/SurfMaps1/main/maps/surf_crzyfrog_reloaded_fix/materials/skybox/mpa15_2up.vtf.json?v=2048-99ae"},{"name":"faceNegZ","type":4,"value":"https://raw.githubusercontent.com/RSCSurf/SurfMaps1/main/maps/surf_crzyfrog_reloaded_fix/materials/skybox/mpa15_2dn.vtf.json?v=2048-99ae"}]},"model":0,"classname":"worldspawn"},{"classname":"info_player_terrorist","origin":{"x":9968.0,"y":-2336.0,"z":3187.0},"angles":{"x":0.0,"y":90.0,"z":0.0}},{"classname":"info_player_counterterrorist","origin":{"x":9152.0,"y":-2336.0,"z":3200.0},"angles":{"x":0.0,"y":90.0,"z":0.0}},{"classname":"info_player_counterterrorist","origin":{"x":9216.0,"y":-2336.0,"z":3200.0},"angles":{"x":0.0,"y":90.0,"z":0.0}},{"classname":"info_player_counterterrorist","origin":{"x":9280.0,"y":-2336.0,"z":3200.0},"angles":{"x":0.0,"y":90.0,"z":0.0}},{"classname":"info_player_counterterrorist","origin":{"x":9344.0,"y":-2336.0,"z":3200.0},"angles":{"x":0.0,"y":90.0,"z":0.0}},{"classname":"info_player_counterterrorist","origin":{"x":9408.0,"y":-2336.0,"z":3200.0},"angles":{"x":0.0,"y":90.0,"z":0.0}},{"classname":"info_player_counterterrorist","origin":{"x":9472.0,"y":-2336.0,"z":3200.0},"angles":{"x":0.0,"y":90.0,"z":0.0}},{"classname":"info_player_counterterrorist","origin":{"x":9536.0,"y":-2336.0,"z":3200.0},"angles":{"x":0.0,"y":90.0,"z":0.0}},{"classname":"info_player_counterterrorist","origin":{"x":9600.0,"y":-2336.0,"z":3200.0},"angles":{"x":0.0,"y":90.0,"z":0.0}},{"classname":"info_player_counterterrorist","origin":{"x":9664.0,"y":-2336.0,"z":3200.0},"angles":{"x":0.0,"y":90.0,"z":0.0}},{"classname":"info_player_counterterrorist","origin":{"x":9728.0,"y":-2336.0,"z":3200.0},"angles":{"x":0.0,"y":90.0,"z":0.0}},{"classname":"info_player_counterterrorist","origin":{"x":9728.0,"y":-2416.0,"z":3200.0},"angles":{"x":0.0,"y":90.0,"z":0.0}},{"classname":"info_player_counterterrorist","origin":{"x":9664.0,"y":-2416.0,"z":3200.0},"angles":{"x":0.0,"y":90.0,"z":0.0}},{"classname":"info_player_counterterrorist","origin":{"x":9600.0,"y":-2416.0,"z":3200.0},"angles":{"x":0.0,"y":90.0,"z":0.0}},{"classname":"info_player_counterterrorist","origin":{"x":9536.0,"y":-2416.0,"z":3200.0},"angles":{"x":0.0,"y":90.0,"z":0.0}},{"classname":"info_player_counterterrorist","origin":{"x":9472.0,"y":-2416.0,"z":3200.0},"angles":{"x":0.0,"y":90.0,"z":0.0}},{"classname":"info_player_counterterrorist","origin":{"x":9408.0,"y":-2416.0,"z":3200.0},"angles":{"x":0.0,"y":90.0,"z":0.0}},{"classname":"info_player_counterterrorist","origin":{"x":9344.0,"y":-2416.0,"z":3200.0},"angles":{"x":0.0,"y":90.0,"z":0.0}},{"classname":"info_player_counterterrorist","origin":{"x":9280.0,"y":-2416.0,"z":3200.0},"angles":{"x":0.0,"y":90.0,"z":0.0}},{"classname":"info_player_counterterrorist","origin":{"x":9216.0,"y":-2416.0,"z":3200.0},"angles":{"x":0.0,"y":90.0,"z":0.0}},{"classname":"info_player_counterterrorist","origin":{"x":9152.0,"y":-2416.0,"z":3200.0},"angles":{"x":0.0,"y":90.0,"z":0.0}},{"classname":"info_player_counterterrorist","origin":{"x":9728.0,"y":-2512.0,"z":3200.0},"angles":{"x":0.0,"y":90.0,"z":0.0}},{"classname":"info_player_counterterrorist","origin":{"x":9664.0,"y":-2512.0,"z":3200.0},"angles":{"x":0.0,"y":90.0,"z":0.0}},{"classname":"info_player_counterterrorist","origin":{"x":9600.0,"y":-2512.0,"z":3200.0},"angles":{"x":0.0,"y":90.0,"z":0.0}},{"classname":"info_player_counterterrorist","origin":{"x":9536.0,"y":-2512.0,"z":3200.0},"angles":{"x":0.0,"y":90.0,"z":0.0}},{"classname":"info_player_counterterrorist","origin":{"x":9472.0,"y":-2512.0,"z":3200.0},"angles":{"x":0.0,"y":90.0,"z":0.0}},{"classname":"info_player_counterterrorist","origin":{"x":9408.0,"y":-2512.0,"z":3200.0},"angles":{"x":0.0,"y":90.0,"z":0.0}},{"classname":"info_player_counterterrorist","origin":{"x":9344.0,"y":-2512.0,"z":3200.0},"angles":{"x":0.0,"y":90.0,"z":0.0}},{"classname":"info_player_counterterrorist","origin":{"x":9280.0,"y":-2512.0,"z":3200.0},"angles":{"x":0.0,"y":90.0,"z":0.0}},{"classname":"info_player_counterterrorist","origin":{"x":9216.0,"y":-2512.0,"z":3200.0},"angles":{"x":0.0,"y":90.0,"z":0.0}},{"classname":"info_player_counterterrorist","origin":{"x":9152.0,"y":-2512.0,"z":3200.0},"angles":{"x":0.0,"y":90.0,"z":0.0}},{"classname":"info_player_terrorist","origin":{"x":10032.0,"y":-2336.0,"z":3187.0},"angles":{"x":0.0,"y":90.0,"z":0.0}},{"classname":"info_player_terrorist","origin":{"x":10096.0,"y":-2336.0,"z":3187.0},"angles":{"x":0.0,"y":90.0,"z":0.0}},{"classname":"info_player_terrorist","origin":{"x":10160.0,"y":-2336.0,"z":3187.0},"angles":{"x":0.0,"y":90.0,"z":0.0}},{"classname":"info_player_terrorist","origin":{"x":10224.0,"y":-2336.0,"z":3187.0},"angles":{"x":0.0,"y":90.0,"z":0.0}},{"classname":"info_player_terrorist","origin":{"x":10288.0,"y":-2336.0,"z":3187.0},"angles":{"x":0.0,"y":90.0,"z":0.0}},{"classname":"info_player_terrorist","origin":{"x":10352.0,"y":-2336.0,"z":3187.0},"angles":{"x":0.0,"y":90.0,"z":0.0}},{"classname":"info_player_terrorist","origin":{"x":10416.0,"y":-2336.0,"z":3187.0},"angles":{"x":0.0,"y":90.0,"z":0.0}},{"classname":"info_player_terrorist","origin":{"x":10480.0,"y":-2336.0,"z":3187.0},"angles":{"x":0.0,"y":90.0,"z":0.0}},{"classname":"info_player_terrorist","origin":{"x":10560.0,"y":-2336.0,"z":3187.0},"angles":{"x":0.0,"y":90.0,"z":0.0}},{"classname":"info_player_terrorist","origin":{"x":10560.0,"y":-2400.0,"z":3187.0},"angles":{"x":0.0,"y":90.0,"z":0.0}},{"classname":"info_player_terrorist","origin":{"x":10480.0,"y":-2400.0,"z":3187.0},"angles":{"x":0.0,"y":90.0,"z":0.0}},{"classname":"info_player_terrorist","origin":{"x":10416.0,"y":-2400.0,"z":3187.0},"angles":{"x":0.0,"y":90.0,"z":0.0}},{"classname":"info_player_terrorist","origin":{"x":10352.0,"y":-2400.0,"z":3187.0},"angles":{"x":0.0,"y":90.0,"z":0.0}},{"classname":"info_player_terrorist","origin":{"x":10288.0,"y":-2400.0,"z":3187.0},"angles":{"x":0.0,"y":90.0,"z":0.0}},{"classname":"info_player_terrorist","origin":{"x":10224.0,"y":-2400.0,"z":3187.0},"angles":{"x":0.0,"y":90.0,"z":0.0}},{"classname":"info_player_terrorist","origin":{"x":10160.0,"y":-2400.0,"z":3187.0},"angles":{"x":0.0,"y":90.0,"z":0.0}},{"classname":"info_player_terrorist","origin":{"x":10096.0,"y":-2400.0,"z":3187.0},"angles":{"x":0.0,"y":90.0,"z":0.0}},{"classname":"info_player_terrorist","origin":{"x":10032.0,"y":-2400.0,"z":3187.0},"angles":{"x":0.0,"y":90.0,"z":0.0}},{"classname":"info_player_terrorist","origin":{"x":9968.0,"y":-2400.0,"z":3187.0},"angles":{"x":0.0,"y":90.0,"z":0.0}},{"classname":"info_player_terrorist","origin":{"x":10560.0,"y":-2464.0,"z":3187.0},"angles":{"x":0.0,"y":90.0,"z":0.0}},{"classname":"info_player_terrorist","origin":{"x":10480.0,"y":-2464.0,"z":3187.0},"angles":{"x":0.0,"y":90.0,"z":0.0}},{"classname":"info_player_terrorist","origin":{"x":10416.0,"y":-2464.0,"z":3187.0},"angles":{"x":0.0,"y":90.0,"z":0.0}},{"classname":"info_player_terrorist","origin":{"x":10352.0,"y":-2464.0,"z":3187.0},"angles":{"x":0.0,"y":90.0,"z":0.0}},{"classname":"info_player_terrorist","origin":{"x":10288.0,"y":-2464.0,"z":3187.0},"angles":{"x":0.0,"y":90.0,"z":0.0}},{"classname":"info_player_terrorist","origin":{"x":10224.0,"y":-2464.0,"z":3187.0},"angles":{"x":0.0,"y":90.0,"z":0.0}},{"classname":"info_player_terrorist","origin":{"x":10160.0,"y":-2464.0,"z":3187.0},"angles":{"x":0.0,"y":90.0,"z":0.0}},{"classname":"info_player_terrorist","origin":{"x":10096.0,"y":-2464.0,"z":3187.0},"angles":{"x":0.0,"y":90.0,"z":0.0}},{"classname":"info_player_terrorist","origin":{"x":10032.0,"y":-2464.0,"z":3187.0},"angles":{"x":0.0,"y":90.0,"z":0.0}},{"classname":"info_player_terrorist","origin":{"x":9968.0,"y":-2464.0,"z":3187.0},"angles":{"x":0.0,"y":90.0,"z":0.0}},{"classname":"info_player_terrorist","origin":{"x":10560.0,"y":-2544.0,"z":3187.0},"angles":{"x":0.0,"y":90.0,"z":0.0}},{"classname":"info_player_terrorist","origin":{"x":10480.0,"y":-2544.0,"z":3187.0},"angles":{"x":0.0,"y":90.0,"z":0.0}},{"classname":"info_player_counterterrorist","origin":{"x":9728.0,"y":-2576.0,"z":3200.0},"angles":{"x":0.0,"y":90.0,"z":0.0}},{"classname":"info_player_counterterrorist","origin":{"x":9664.0,"y":-2576.0,"z":3200.0},"angles":{"x":0.0,"y":90.0,"z":0.0}},{"classname":"trigger_push","origin":{"x":-8883.02,"y":7641.9,"z":6991.5}},{"classname":"trigger_push","origin":{"x":-8883.02,"y":6314.1,"z":6991.5}},{"classname":"env_spritetrail","origin":{"x":9132.0,"y":-4135.0,"z":3159.0}},{"targetname":"beamerrotating1","classname":"momentary_rot_button","origin":{"x":9132.01,"y":-4115.04,"z":3159.0},"angles":{"x":0.0,"y":0.0,"z":0.0}},{"classname":"env_spritetrail","origin":{"x":9132.0,"y":-4095.0,"z":3159.0}},{"classname":"env_spritetrail","origin":{"x":9132.0,"y":-3396.0,"z":3159.0}},{"targetname":"beamerrotating2","classname":"momentary_rot_button","origin":{"x":9132.01,"y":-3376.04,"z":3159.0},"angles":{"x":0.0,"y":0.0,"z":0.0}},{"classname":"env_spritetrail","origin":{"x":9132.0,"y":-3356.0,"z":3159.0}},{"classname":"env_spritetrail","origin":{"x":10620.0,"y":-3396.0,"z":3159.0}},{"targetname":"beamerrotating3","classname":"momentary_rot_button","origin":{"x":10620.0,"y":-3376.04,"z":3159.0},"angles":{"x":0.0,"y":0.0,"z":0.0}},{"classname":"env_spritetrail","origin":{"x":10620.0,"y":-3356.0,"z":3159.0}},{"classname":"env_spritetrail","origin":{"x":10620.0,"y":-4135.0,"z":3159.0}},{"targetname":"beamerrotating4","classname":"momentary_rot_button","origin":{"x":10620.0,"y":-4115.04,"z":3159.0},"angles":{"x":0.0,"y":0.0,"z":0.0}},{"classname":"env_spritetrail","origin":{"x":10620.0,"y":-4095.0,"z":3159.0}},{"classname":"point_spotlight","origin":{"x":5578.0,"y":-5084.0,"z":-3473.01},"angles":{"x":-90.0,"y":90.0,"z":0.0}},{"classname":"point_spotlight","origin":{"x":5311.0,"y":-5141.0,"z":-3473.01},"angles":{"x":-90.0,"y":90.0,"z":0.0}},{"classname":"point_spotlight","origin":{"x":5037.0,"y":-5091.0,"z":-3473.01},"angles":{"x":-90.0,"y":90.0,"z":0.0}},{"classname":"point_spotlight","origin":{"x":4805.0,"y":-4947.0,"z":-3473.01},"angles":{"x":-90.0,"y":90.0,"z":0.0}},{"classname":"point_spotlight","origin":{"x":4644.01,"y":-4722.89,"z":-3473.01},"angles":{"x":-90.0,"y":90.0,"z":0.0}},{"classname":"point_spotlight","origin":{"x":4583.01,"y":-4423.89,"z":-3473.01},"angles":{"x":-90.0,"y":90.0,"z":0.0}},{"classname":"point_spotlight","origin":{"x":4634.01,"y":-4173.89,"z":-3473.01},"angles":{"x":-90.0,"y":90.0,"z":0.0}},{"classname":"point_spotlight","origin":{"x":4785.0,"y":-3945.0,"z":-3473.01},"angles":{"x":-90.0,"y":90.0,"z":0.0}},{"classname":"point_spotlight","origin":{"x":5015.0,"y":-3790.0,"z":-3473.01},"angles":{"x":-90.0,"y":90.0,"z":0.0}},{"classname":"point_spotlight","origin":{"x":5282.0,"y":-3734.0,"z":-3473.01},"angles":{"x":-90.0,"y":90.0,"z":0.0}},{"classname":"point_spotlight","origin":{"x":5556.0,"y":-3781.0,"z":-3473.01},"angles":{"x":-90.0,"y":90.0,"z":0.0}},{"classname":"point_spotlight","origin":{"x":5786.0,"y":-3924.0,"z":-3473.01},"angles":{"x":-90.0,"y":90.0,"z":0.0}},{"classname":"point_spotlight","origin":{"x":5950.01,"y":-4150.89,"z":-3473.01},"angles":{"x":-90.0,"y":90.0,"z":0.0}},{"classname":"point_spotlight","origin":{"x":6012.0,"y":-4425.0,"z":-3473.01},"angles":{"x":-90.0,"y":90.0,"z":0.0}},{"classname":"point_spotlight","origin":{"x":5962.01,"y":-4697.89,"z":-3473.01},"angles":{"x":-90.0,"y":90.0,"z":0.0}},{"classname":"point_spotlight","origin":{"x":5808.0,"y":-4931.0,"z":-3473.01},"angles":{"x":-90.0,"y":90.0,"z":0.0}},{"classname":"point_spotlight","origin":{"x":14733.0,"y":-5077.01,"z":-3473.01},"angles":{"x":-90.0,"y":90.0,"z":0.0}},{"classname":"point_spotlight","origin":{"x":14466.0,"y":-5134.01,"z":-3473.01},"angles":{"x":-90.0,"y":90.0,"z":0.0}},{"classname":"point_spotlight","origin":{"x":14192.0,"y":-5084.01,"z":-3473.01},"angles":{"x":-90.0,"y":90.0,"z":0.0}},{"classname":"point_spotlight","origin":{"x":13960.0,"y":-4940.01,"z":-3473.01},"angles":{"x":-90.0,"y":90.0,"z":0.0}},{"classname":"point_spotlight","origin":{"x":13799.0,"y":-4715.9,"z":-3473.01},"angles":{"x":-90.0,"y":90.0,"z":0.0}},{"classname":"point_spotlight","origin":{"x":13738.0,"y":-4416.9,"z":-3473.01},"angles":{"x":-90.0,"y":90.0,"z":0.0}},{"classname":"point_spotlight","origin":{"x":13789.0,"y":-4166.9,"z":-3473.01},"angles":{"x":-90.0,"y":90.0,"z":0.0}},{"classname":"point_spotlight","origin":{"x":13940.0,"y":-3938.01,"z":-3473.01},"angles":{"x":-90.0,"y":90.0,"z":0.0}},{"classname":"point_spotlight","origin":{"x":14170.0,"y":-3783.01,"z":-3473.01},"angles":{"x":-90.0,"y":90.0,"z":0.0}},{"classname":"point_spotlight","origin":{"x":14437.0,"y":-3727.01,"z":-3473.01},"angles":{"x":-90.0,"y":90.0,"z":0.0}},{"classname":"point_spotlight","origin":{"x":14711.0,"y":-3774.01,"z":-3473.01},"angles":{"x":-90.0,"y":90.0,"z":0.0}},{"classname":"point_spotlight","origin":{"x":14941.0,"y":-3917.01,"z":-3473.01},"angles":{"x":-90.0,"y":90.0,"z":0.0}},{"classname":"point_spotlight","origin":{"x":15105.0,"y":-4143.9,"z":-3473.01},"angles":{"x":-90.0,"y":90.0,"z":0.0}},{"classname":"point_spotlight","origin":{"x":15167.0,"y":-4418.01,"z":-3473.01},"angles":{"x":-90.0,"y":90.0,"z":0.0}},{"classname":"point_spotlight","origin":{"x":15117.0,"y":-4690.9,"z":-3473.01},"angles":{"x":-90.0,"y":90.0,"z":0.0}},{"classname":"point_spotlight","origin":{"x":14963.0,"y":-4924.01,"z":-3473.01},"angles":{"x":-90.0,"y":90.0,"z":0.0}},{"model":7,"clusters":[369,370],"classname":"func_brush","origin":{"x":5290.0,"y":-4730.5,"z":-4389.0}},{"model":8,"clusters":[238,239],"classname":"func_brush","origin":{"x":14456.0,"y":-4697.5,"z":-4389.0}},{"classname":"point_spotlight","origin":{"x":10200.0,"y":7657.1,"z":999.03},"angles":{"x":-90.0,"y":90.0,"z":0.0}},{"classname":"point_spotlight","origin":{"x":10200.0,"y":7581.1,"z":999.03},"angles":{"x":-90.0,"y":90.0,"z":0.0}},{"classname":"point_spotlight","origin":{"x":10200.0,"y":7508.1,"z":999.03},"angles":{"x":-90.0,"y":90.0,"z":0.0}},{"classname":"point_spotlight","origin":{"x":10188.0,"y":7436.1,"z":999.03},"angles":{"x":-90.0,"y":90.0,"z":0.0}},{"classname":"point_spotlight","origin":{"x":10142.0,"y":7349.1,"z":999.03},"angles":{"x":-90.0,"y":90.0,"z":0.0}},{"classname":"point_spotlight","origin":{"x":10067.0,"y":7288.1,"z":999.03},"angles":{"x":-90.0,"y":90.0,"z":0.0}},{"classname":"point_spotlight","origin":{"x":9973.0,"y":7259.1,"z":999.03},"angles":{"x":-90.0,"y":90.0,"z":0.0}},{"classname":"point_spotlight","origin":{"x":9876.0,"y":7257.1,"z":999.03},"angles":{"x":-90.0,"y":90.0,"z":0.0}},{"classname":"point_spotlight","origin":{"x":9779.0,"y":7260.1,"z":999.03},"angles":{"x":-90.0,"y":90.0,"z":0.0}},{"classname":"point_spotlight","origin":{"x":9686.0,"y":7288.1,"z":999.03},"angles":{"x":-90.0,"y":90.0,"z":0.0}},{"classname":"point_spotlight","origin":{"x":9610.0,"y":7350.1,"z":999.03},"angles":{"x":-90.0,"y":90.0,"z":0.0}},{"classname":"point_spotlight","origin":{"x":9564.0,"y":7436.1,"z":999.03},"angles":{"x":-90.0,"y":90.0,"z":0.0}},{"classname":"point_spotlight","origin":{"x":9552.0,"y":7509.1,"z":999.03},"angles":{"x":-90.0,"y":90.0,"z":0.0}},{"classname":"point_spotlight","origin":{"x":9552.0,"y":7581.1,"z":999.03},"angles":{"x":-90.0,"y":90.0,"z":0.0}},{"classname":"point_spotlight","origin":{"x":9552.0,"y":7657.1,"z":999.03},"angles":{"x":-90.0,"y":90.0,"z":0.0}},{"classname":"light","origin":{"x":9876.0,"y":7741.0,"z":1138.0}},{"classname":"light","origin":{"x":10296.0,"y":-2691.0,"z":3343.0}},{"classname":"light","origin":{"x":5297.0,"y":-4438.0,"z":-3825.0}},{"targetname":"Spawn","classname":"info_teleport_destination","origin":{"x":9876.0,"y":-2448.0,"z":3552.0},"angles":{"x":0.0,"y":90.0,"z":0.0}},{"classname":"light","origin":{"x":14457.0,"y":-4438.0,"z":-3825.0}},{"classname":"light","origin":{"x":14700.0,"y":-4429.0,"z":-4441.0}},{"classname":"light","origin":{"x":5052.0,"y":-4427.0,"z":-4441.0}},{"classname":"water_lod_control","origin":{"x":9924.0,"y":-3195.0,"z":3159.0}},{"classname":"light","origin":{"x":5548.0,"y":-4427.0,"z":-4441.0}},{"classname":"light","origin":{"x":14204.0,"y":-4429.0,"z":-4441.0}},{"classname":"light","origin":{"x":9456.0,"y":-2691.0,"z":3343.0}},{"classname":"light","origin":{"x":9876.0,"y":-1359.0,"z":3075.0}},{"classname":"light","origin":{"x":9876.0,"y":-537.988,"z":1635.0}},{"classname":"light","origin":{"x":9876.0,"y":1104.01,"z":835.0}},{"classname":"light","origin":{"x":9876.0,"y":3245.01,"z":283.0}},{"classname":"light","origin":{"x":9876.0,"y":4565.01,"z":207.0}},{"classname":"light","origin":{"x":8532.0,"y":7741.0,"z":-86.03}},{"classname":"light","origin":{"x":7188.0,"y":7741.0,"z":-86.03}},{"classname":"light","origin":{"x":5844.0,"y":7741.0,"z":-86.0}},{"classname":"light","origin":{"x":12564.0,"y":7741.0,"z":-86.0}},{"classname":"light","origin":{"x":13908.0,"y":7741.0,"z":-86.03}},{"classname":"light","origin":{"x":11220.0,"y":7741.0,"z":-86.03}},{"classname":"light","origin":{"x":9876.0,"y":5889.0,"z":-86.0}},{"classname":"light","origin":{"x":9876.0,"y":283.012,"z":995.0}},{"model":9,"clusters":[300,304,307,308,309,310,311,312,313,314,315,316,319,320],"classname":"func_brush","origin":{"x":9460.0,"y":-3740.0,"z":3151.5}},{"model":10,"clusters":[250,251,252,255,256,257,260,261,262,263,264,265,300,301,302,303,320],"classname":"func_brush","origin":{"x":10292.0,"y":-3740.0,"z":3151.5}},{"targetname":"Stage3 cT","classname":"info_teleport_destination","origin":{"x":9460.0,"y":-3308.0,"z":3400.0},"angles":{"x":0.0,"y":270.0,"z":0.0}},{"targetname":"Stage3 CT","classname":"info_teleport_destination","origin":{"x":10292.0,"y":-3308.0,"z":3400.0},"angles":{"x":0.0,"y":270.0,"z":0.0}},{"model":11,"clusters":[332],"classname":"func_brush","origin":{"x":9877.99,"y":-4649.37,"z":1967.03}},{"model":12,"clusters":[340],"classname":"func_brush","origin":{"x":9878.0,"y":-5242.61,"z":197.01}},{"model":13,"clusters":[412,414],"classname":"func_brush","origin":{"x":7419.0,"y":-8549.0,"z":4689.5}},{"classname":"trigger_multiple","origin":{"x":7419.0,"y":-8428.0,"z":432.54}},{"model":15,"clusters":[553],"classname":"func_brush","origin":{"x":9584.0,"y":-12803.5,"z":-65.0}},{"model":16,"clusters":[553],"classname":"func_brush","origin":{"x":9584.0,"y":-12803.5,"z":-1831.0}},{"classname":"trigger_multiple","origin":{"x":1457.0,"y":-8549.5,"z":-5273.81}},{"model":18,"clusters":[377],"classname":"func_brush","origin":{"x":8619.5,"y":-8094.0,"z":4627.0}},{"model":19,"clusters":[403],"classname":"func_brush","origin":{"x":8619.5,"y":-8394.0,"z":4628.0}},{"model":20,"clusters":[403],"classname":"func_brush","origin":{"x":8619.5,"y":-8994.0,"z":4628.0}},{"classname":"trigger_teleport","origin":{"x":8619.0,"y":-8994.0,"z":4527.0}},{"model":22,"clusters":[359,360],"classname":"func_brush","origin":{"x":9132.5,"y":-4114.0,"z":3259.0}},{"model":23,"clusters":[359],"classname":"func_brush","origin":{"x":9132.5,"y":-3376.0,"z":3260.15}},{"model":24,"clusters":[246,322],"classname":"func_brush","origin":{"x":10619.5,"y":-4116.0,"z":3259.0}},{"model":25,"clusters":[246],"classname":"func_brush","origin":{"x":10619.5,"y":-3376.0,"z":3260.0}},{"classname":"point_spotlight","origin":{"x":10292.0,"y":-3740.0,"z":3577.02},"angles":{"x":90.0,"y":270.0,"z":0.0}},{"classname":"point_spotlight","origin":{"x":9460.01,"y":-3739.97,"z":3577.02},"angles":{"x":90.0,"y":270.0,"z":0.0}},{"classname":"light","origin":{"x":9460.0,"y":-3740.0,"z":3359.0}},{"classname":"light","origin":{"x":10292.0,"y":-3740.0,"z":3359.0}},{"classname":"light","origin":{"x":9876.0,"y":-5313.0,"z":2831.0}},{"classname":"light","origin":{"x":9876.0,"y":-6337.0,"z":815.0}},{"classname":"light","origin":{"x":9876.0,"y":-7361.0,"z":-1426.0}},{"classname":"light","origin":{"x":9876.0,"y":-10049.0,"z":-2570.0}},{"classname":"light","origin":{"x":5620.0,"y":-14767.0,"z":-977.0}},{"classname":"light","origin":{"x":3828.0,"y":-14767.0,"z":-977.0}},{"classname":"light","origin":{"x":2068.0,"y":-14767.0,"z":-977.0}},{"classname":"light","origin":{"x":-526.998,"y":-14767.0,"z":-977.0}},{"classname":"point_spotlight","origin":{"x":9960.0,"y":-12806.8,"z":-1322.0},"angles":{"x":0.0,"y":180.0,"z":0.0}},{"classname":"point_spotlight","origin":{"x":9958.0,"y":-12806.8,"z":-572.0},"angles":{"x":90.0,"y":180.0,"z":0.0}},{"classname":"point_spotlight","origin":{"x":9208.0,"y":-12806.8,"z":-574.0},"angles":{"x":0.0,"y":0.0,"z":180.0}},{"classname":"point_spotlight","origin":{"x":9210.0,"y":-12806.8,"z":-1324.0},"angles":{"x":-90.0,"y":180.0,"z":0.0}},{"classname":"light","origin":{"x":9876.0,"y":-11745.0,"z":-2570.0}},{"classname":"light","origin":{"x":9892.0,"y":-5969.0,"z":1958.0}},{"classname":"light","origin":{"x":9892.0,"y":-6859.0,"z":-471.0}},{"classname":"light","origin":{"x":628.001,"y":-14767.0,"z":-977.0}},{"classname":"light","origin":{"x":-2572.0,"y":-14767.0,"z":-977.0}},{"classname":"light","origin":{"x":-2190.0,"y":-8549.0,"z":-3192.0}},{"classname":"light","origin":{"x":2228.0,"y":-8549.0,"z":-3278.0}},{"model":26,"clusters":[956,957],"classname":"func_brush","origin":{"x":-10405.0,"y":-6838.0,"z":-3501.0}},{"model":27,"clusters":[957],"classname":"func_brush","origin":{"x":-10405.0,"y":-6838.0,"z":-4657.0}},{"classname":"trigger_teleport","origin":{"x":-10405.0,"y":-6838.0,"z":-8373.0}},{"classname":"trigger_teleport","origin":{"x":-10405.0,"y":-6838.0,"z":-8373.0}},{"classname":"light","origin":{"x":-10405.0,"y":-6838.0,"z":-1670.0}},{"classname":"light","origin":{"x":-10405.0,"y":-6838.0,"z":-2534.0}},{"classname":"light","origin":{"x":-10405.0,"y":-6838.0,"z":-3398.0}},{"classname":"light","origin":{"x":-10405.0,"y":-6838.0,"z":-4262.0}},{"classname":"light","origin":{"x":-10405.0,"y":-6838.0,"z":-5126.0}},{"classname":"light","origin":{"x":-10405.0,"y":-6838.0,"z":-5990.0}},{"classname":"light","origin":{"x":-10405.0,"y":-6838.0,"z":-6854.0}},{"classname":"light","origin":{"x":-10405.0,"y":-6838.0,"z":-7718.0}},{"classname":"trigger_teleport","origin":{"x":1130.5,"y":701.5,"z":2383.0}},{"classname":"light","origin":{"x":-10405.0,"y":-6838.0,"z":-777.0}},{"classname":"light","origin":{"x":-9134.34,"y":6062.0,"z":7178.08}},{"classname":"light","origin":{"x":-10405.0,"y":-6520.0,"z":-8468.0}},{"Brightness":{"R":255,"G":198,"B":140,"A":194},"Ambient":{"R":255,"G":255,"B":255,"A":20},"BrightnessHdr":{"R":255,"G":255,"B":255,"A":1},"AmbientHdr":{"R":255,"G":255,"B":255,"A":1},"BrightnessScaleHdr":1.0,"AmbientScaleHdr":1.0,"Pitch":-45.0,"classname":"light_environment","origin":{"x":9940.0,"y":-3195.0,"z":3159.0},"angles":{"x":0.0,"y":0.0,"z":0.0}},{"classname":"light","origin":{"x":9876.0,"y":-7674.0,"z":2880.0}},{"classname":"light","origin":{"x":9876.0,"y":-7739.0,"z":2049.0}},{"classname":"light","origin":{"x":9876.0,"y":-7732.0,"z":538.0}},{"classname":"light","origin":{"x":9876.0,"y":-8157.0,"z":-474.0}},{"classname":"light","origin":{"x":9876.0,"y":-10049.0,"z":-1366.0}},{"classname":"light","origin":{"x":9876.0,"y":-11745.0,"z":-1366.0}},{"classname":"light","origin":{"x":9876.0,"y":-10049.0,"z":-16.0}},{"classname":"light","origin":{"x":9876.0,"y":-11745.0,"z":-16.0}},{"classname":"light","origin":{"x":-2572.0,"y":-14767.0,"z":-1800.0}},{"classname":"light","origin":{"x":-526.999,"y":-14767.0,"z":-1800.0}},{"classname":"light","origin":{"x":628.0,"y":-14767.0,"z":-1800.0}},{"classname":"light","origin":{"x":2068.0,"y":-14767.0,"z":-1800.0}},{"classname":"light","origin":{"x":3828.0,"y":-14767.0,"z":-1800.0}},{"classname":"light","origin":{"x":-2572.0,"y":-14767.0,"z":-2456.0}},{"classname":"light","origin":{"x":-526.999,"y":-14767.0,"z":-2456.0}},{"classname":"light","origin":{"x":628.0,"y":-14767.0,"z":-2456.0}},{"classname":"light","origin":{"x":2068.0,"y":-14767.0,"z":-2456.0}},{"classname":"light","origin":{"x":-2572.0,"y":-14767.0,"z":-2977.0}},{"classname":"light","origin":{"x":-526.999,"y":-14767.0,"z":-2977.0}},{"classname":"light","origin":{"x":628.0,"y":-14767.0,"z":-2977.0}},{"classname":"light","origin":{"x":-2572.0,"y":-14767.0,"z":-3400.0}},{"classname":"light","origin":{"x":-526.999,"y":-14767.0,"z":-3400.0}},{"classname":"light","origin":{"x":-4044.0,"y":-14767.0,"z":-3399.0}},{"classname":"light","origin":{"x":-4044.0,"y":-14767.0,"z":-2976.0}},{"classname":"light","origin":{"x":-4044.0,"y":-14767.0,"z":-2455.0}},{"classname":"light","origin":{"x":-4044.0,"y":-14767.0,"z":-1799.0}},{"classname":"light","origin":{"x":-4044.0,"y":-14767.0,"z":-976.0}},{"classname":"light","origin":{"x":-4044.0,"y":-12370.0,"z":-3399.0}},{"classname":"light","origin":{"x":-4044.0,"y":-12370.0,"z":-2976.0}},{"classname":"light","origin":{"x":-4044.0,"y":-12370.0,"z":-2455.0}},{"classname":"light","origin":{"x":-4044.0,"y":-12370.0,"z":-1799.0}},{"classname":"light","origin":{"x":-4044.0,"y":-12370.0,"z":-976.0}},{"classname":"light","origin":{"x":-4044.0,"y":-10932.0,"z":-3799.0}},{"classname":"light","origin":{"x":-4044.0,"y":-10932.0,"z":-4222.0}},{"classname":"light","origin":{"x":-4044.0,"y":-10932.0,"z":-3278.0}},{"classname":"light","origin":{"x":-4044.0,"y":-10932.0,"z":-2622.0}},{"classname":"light","origin":{"x":-4044.0,"y":-10932.0,"z":-1799.0}},{"classname":"light","origin":{"x":-4044.0,"y":-8549.0,"z":-4222.0}},{"classname":"light","origin":{"x":-4044.0,"y":-8549.0,"z":-3799.0}},{"classname":"light","origin":{"x":-4044.0,"y":-8549.0,"z":-3278.0}},{"classname":"light","origin":{"x":-4044.0,"y":-8549.0,"z":-2622.0}},{"classname":"light","origin":{"x":-4044.0,"y":-8549.0,"z":-1799.0}},{"classname":"light","origin":{"x":-4044.0,"y":-10932.0,"z":-976.0}},{"classname":"light","origin":{"x":-4044.0,"y":-8549.0,"z":-976.0}},{"classname":"light","origin":{"x":-2190.0,"y":-8549.0,"z":-4024.0}},{"classname":"light","origin":{"x":-524.0,"y":-8549.0,"z":-4024.0}},{"classname":"light","origin":{"x":-524.0,"y":-8549.0,"z":-3192.0}},{"classname":"light","origin":{"x":-524.0,"y":-8549.0,"z":-4864.0}},{"classname":"light","origin":{"x":578.0,"y":-8550.0,"z":-4864.0}},{"classname":"light","origin":{"x":578.0,"y":-8550.0,"z":-3192.0}},{"classname":"light","origin":{"x":578.0,"y":-8550.0,"z":-4024.0}},{"classname":"light","origin":{"x":5012.0,"y":-8549.0,"z":-2520.0}},{"classname":"light","origin":{"x":2228.0,"y":-8549.0,"z":-5275.0}},{"classname":"light","origin":{"x":4017.0,"y":-8549.0,"z":-5275.0}},{"classname":"light","origin":{"x":6554.0,"y":-8549.0,"z":-5275.0}},{"classname":"light","origin":{"x":6554.0,"y":-8549.0,"z":-4616.0}},{"classname":"light","origin":{"x":2228.0,"y":-8549.0,"z":-4616.0}},{"classname":"light","origin":{"x":4017.0,"y":-8549.0,"z":-4616.0}},{"classname":"light","origin":{"x":6554.0,"y":-8549.0,"z":-3856.0}},{"classname":"light","origin":{"x":4017.0,"y":-8549.0,"z":-4104.0}},{"classname":"light","origin":{"x":9876.0,"y":-537.988,"z":3075.0}},{"classname":"light","origin":{"x":9876.0,"y":283.012,"z":1635.0}},{"classname":"light","origin":{"x":9876.0,"y":283.012,"z":3075.0}},{"classname":"light","origin":{"x":9876.0,"y":-537.988,"z":2335.0}},{"classname":"light","origin":{"x":9876.0,"y":283.012,"z":2335.0}},{"classname":"light","origin":{"x":9876.0,"y":1104.01,"z":1635.0}},{"classname":"light","origin":{"x":9876.0,"y":1104.01,"z":2335.0}},{"classname":"light","origin":{"x":9876.0,"y":1104.01,"z":3075.0}},{"classname":"light","origin":{"x":5300.0,"y":5889.0,"z":-86.0}},{"classname":"light","origin":{"x":14452.0,"y":5889.0,"z":-86.03}},{"classname":"light","origin":{"x":5300.0,"y":3968.0,"z":-1289.0}},{"classname":"light","origin":{"x":14452.0,"y":3968.0,"z":-1289.0}},{"classname":"light","origin":{"x":5300.0,"y":2056.0,"z":-2616.0}},{"classname":"light","origin":{"x":14452.0,"y":2056.0,"z":-2616.0}},{"classname":"light","origin":{"x":5300.0,"y":-572.0,"z":-2679.0}},{"classname":"light","origin":{"x":14452.0,"y":-572.0,"z":-2679.0}},{"classname":"light","origin":{"x":5300.0,"y":-3203.0,"z":-2092.0}},{"classname":"light","origin":{"x":14452.0,"y":-3203.0,"z":-2092.0}},{"classname":"point_spotlight","origin":{"x":9124.58,"y":-3074.89,"z":3151.0},"angles":{"x":-90.0,"y":90.0,"z":0.0}},{"classname":"point_spotlight","origin":{"x":9124.58,"y":-2946.89,"z":3151.0},"angles":{"x":-90.0,"y":90.0,"z":0.0}},{"classname":"point_spotlight","origin":{"x":9124.55,"y":-2818.88,"z":3151.0},"angles":{"x":-90.0,"y":90.0,"z":0.0}},{"classname":"point_spotlight","origin":{"x":9124.55,"y":-2690.88,"z":3151.0},"angles":{"x":-90.0,"y":90.0,"z":0.0}},{"classname":"point_spotlight","origin":{"x":9124.55,"y":-2562.88,"z":3151.0},"angles":{"x":-90.0,"y":90.0,"z":0.0}},{"classname":"point_spotlight","origin":{"x":9124.55,"y":-2434.88,"z":3151.0},"angles":{"x":-90.0,"y":90.0,"z":0.0}},{"classname":"point_spotlight","origin":{"x":9125.0,"y":-2306.89,"z":3151.0},"angles":{"x":-90.0,"y":90.0,"z":0.0}},{"classname":"point_spotlight","origin":{"x":10627.3,"y":-2690.88,"z":3151.0},"angles":{"x":-90.0,"y":90.0,"z":0.0}},{"classname":"point_spotlight","origin":{"x":10627.3,"y":-2562.88,"z":3151.0},"angles":{"x":-90.0,"y":90.0,"z":0.0}},{"classname":"point_spotlight","origin":{"x":10627.3,"y":-2434.88,"z":3151.0},"angles":{"x":-90.0,"y":90.0,"z":0.0}},{"classname":"point_spotlight","origin":{"x":10627.3,"y":-2306.89,"z":3151.0},"angles":{"x":-90.0,"y":90.0,"z":0.0}},{"classname":"point_spotlight","origin":{"x":10627.3,"y":-2818.88,"z":3151.0},"angles":{"x":-90.0,"y":90.0,"z":0.0}},{"classname":"point_spotlight","origin":{"x":10627.3,"y":-2946.89,"z":3151.0},"angles":{"x":-90.0,"y":90.0,"z":0.0}},{"classname":"point_spotlight","origin":{"x":10627.3,"y":-3074.89,"z":3151.0},"angles":{"x":-90.0,"y":90.0,"z":0.0}},{"classname":"light","origin":{"x":-9134.34,"y":7893.3,"z":7178.08}},{"classname":"light","origin":{"x":-8965.0,"y":7412.0,"z":6727.0}},{"classname":"light","origin":{"x":-8965.0,"y":7412.0,"z":5603.0}},{"classname":"light","origin":{"x":-8965.0,"y":7412.0,"z":4483.0}},{"classname":"light","origin":{"x":-7669.0,"y":6978.0,"z":6727.0}},{"classname":"light","origin":{"x":-6209.0,"y":6978.0,"z":6727.0}},{"classname":"light","origin":{"x":-6209.0,"y":6978.0,"z":5603.0}},{"classname":"light","origin":{"x":-3791.0,"y":6978.0,"z":6727.0}},{"classname":"light","origin":{"x":-3791.0,"y":6978.0,"z":5603.0}},{"classname":"light","origin":{"x":-2482.0,"y":6506.0,"z":6727.0}},{"classname":"light","origin":{"x":-2482.0,"y":6506.0,"z":5603.0}},{"classname":"light","origin":{"x":-1910.0,"y":5409.0,"z":6727.0}},{"classname":"light","origin":{"x":-1910.0,"y":5409.0,"z":5603.0}},{"classname":"light","origin":{"x":-3791.0,"y":6978.0,"z":4560.0}},{"classname":"light","origin":{"x":-2482.0,"y":6506.0,"z":4560.0}},{"classname":"light","origin":{"x":-1910.0,"y":5409.0,"z":4560.0}},{"classname":"light","origin":{"x":-1639.0,"y":4488.0,"z":4728.0}},{"classname":"light","origin":{"x":-1639.0,"y":3104.0,"z":4359.0}},{"classname":"light","origin":{"x":-1639.0,"y":1416.0,"z":3912.0}},{"classname":"light","origin":{"x":-515.0,"y":3104.0,"z":3465.0}},{"classname":"light","origin":{"x":-515.0,"y":1416.0,"z":3912.0}},{"classname":"light","origin":{"x":602.0,"y":1416.0,"z":3018.0}},{"classname":"light","origin":{"x":602.0,"y":3104.0,"z":3465.0}},{"classname":"light","origin":{"x":1725.0,"y":3104.0,"z":2505.0}},{"classname":"light","origin":{"x":1725.0,"y":1416.0,"z":2952.0}},{"classname":"light","origin":{"x":1131.0,"y":702.0,"z":2384.0}},{"classname":"light","origin":{"x":-1101.0,"y":702.0,"z":3552.0}},{"classname":"light","origin":{"x":51.0,"y":3854.0,"z":2967.0}},{"classname":"light","origin":{"x":1671.0,"y":3850.0,"z":2279.0}},{"classname":"light","origin":{"x":1425.0,"y":5031.0,"z":2278.0}},{"classname":"light","origin":{"x":468.0,"y":6023.0,"z":2278.0}},{"classname":"light","origin":{"x":-1060.0,"y":6320.0,"z":2278.0}},{"classname":"light","origin":{"x":-2112.0,"y":6317.0,"z":1985.0}},{"classname":"light","origin":{"x":-2819.0,"y":6317.0,"z":1707.0}},{"classname":"light","origin":{"x":-3629.0,"y":6317.0,"z":1307.0}},{"classname":"light","origin":{"x":-4352.0,"y":6317.0,"z":960.0}},{"classname":"light","origin":{"x":-4992.0,"y":6317.0,"z":704.0}},{"classname":"light","origin":{"x":-5952.0,"y":6317.0,"z":129.0}},{"classname":"light","origin":{"x":-6784.0,"y":6122.0,"z":-123.0}},{"classname":"light","origin":{"x":-8193.0,"y":5631.0,"z":-513.0}},{"classname":"light","origin":{"x":-9152.0,"y":5106.0,"z":-672.0}},{"classname":"light","origin":{"x":-10019.0,"y":4320.0,"z":-672.0}},{"classname":"light","origin":{"x":-10280.0,"y":3353.0,"z":-672.0}},{"classname":"light","origin":{"x":-10424.0,"y":2605.0,"z":-765.0}},{"classname":"light","origin":{"x":-10424.0,"y":1720.0,"z":-1027.0}},{"classname":"light","origin":{"x":-10424.0,"y":830.0,"z":-1278.0}},{"classname":"light","origin":{"x":-10424.0,"y":-129.0,"z":-1534.0}},{"classname":"light","origin":{"x":-10424.0,"y":-1089.0,"z":-1794.0}},{"classname":"light","origin":{"x":-10424.0,"y":-2561.0,"z":-2172.0}},{"classname":"light","origin":{"x":-10424.0,"y":-3721.0,"z":-2177.0}},{"classname":"light","origin":{"x":-10424.0,"y":-4895.0,"z":-1971.0}},{"classname":"light","origin":{"x":-10424.0,"y":-5377.0,"z":-1151.0}},{"classname":"light","origin":{"x":-10424.0,"y":-5377.0,"z":127.0}},{"classname":"light","origin":{"x":-10424.0,"y":-6275.0,"z":127.0}},{"classname":"light","origin":{"x":-10424.0,"y":-6270.0,"z":-2687.0}},{"classname":"light","origin":{"x":-10424.0,"y":-1866.0,"z":-2003.0}},{"targetname":"beamerrotating5","classname":"momentary_rot_button","origin":{"x":8620.01,"y":-8093.03,"z":4527.0},"angles":{"x":0.0,"y":0.0,"z":0.0}},{"classname":"env_spritetrail","origin":{"x":8620.0,"y":-8073.0,"z":4527.0}},{"classname":"env_spritetrail","origin":{"x":8620.0,"y":-8113.0,"z":4527.0}},{"targetname":"beamerrotating6","classname":"momentary_rot_button","origin":{"x":8620.01,"y":-8394.03,"z":4527.0},"angles":{"x":0.0,"y":0.0,"z":0.0}},{"classname":"env_spritetrail","origin":{"x":8620.0,"y":-8374.0,"z":4527.0}},{"classname":"env_spritetrail","origin":{"x":8620.0,"y":-8414.0,"z":4527.0}},{"targetname":"beamerrotating7","classname":"momentary_rot_button","origin":{"x":8620.01,"y":-8694.03,"z":4527.0},"angles":{"x":0.0,"y":0.0,"z":0.0}},{"classname":"env_spritetrail","origin":{"x":8620.0,"y":-8674.0,"z":4527.0}},{"classname":"env_spritetrail","origin":{"x":8620.0,"y":-8714.0,"z":4527.0}},{"targetname":"beamerrotating8","classname":"momentary_rot_button","origin":{"x":8619.01,"y":-8994.03,"z":4527.0},"angles":{"x":0.0,"y":0.0,"z":0.0}},{"classname":"env_spritetrail","origin":{"x":8619.0,"y":-8974.0,"z":4527.0}},{"classname":"env_spritetrail","origin":{"x":8619.0,"y":-9014.0,"z":4527.0}},{"classname":"logic_auto","origin":{"x":9956.0,"y":-3195.0,"z":3159.0}},{"classname":"env_spritetrail","origin":{"x":5454.0,"y":-4699.0,"z":-4521.0}},{"targetname":"beamerrotating14","classname":"momentary_rot_button","origin":{"x":5434.04,"y":-4699.0,"z":-4521.0},"angles":{"x":0.0,"y":0.0,"z":0.0}},{"classname":"env_spritetrail","origin":{"x":5414.0,"y":-4699.0,"z":-4521.0}},{"classname":"env_spritetrail","origin":{"x":5144.0,"y":-4698.0,"z":-4521.0}},{"classname":"env_spritetrail","origin":{"x":5184.0,"y":-4698.0,"z":-4521.0}},{"targetname":"beamerrotating13","classname":"momentary_rot_button","origin":{"x":5164.04,"y":-4698.0,"z":-4521.0},"angles":{"x":0.0,"y":0.0,"z":0.0}},{"classname":"env_spritetrail","origin":{"x":14310.0,"y":-4698.0,"z":-4521.0}},{"targetname":"beamerrotating11","classname":"momentary_rot_button","origin":{"x":14330.0,"y":-4698.0,"z":-4521.0},"angles":{"x":0.0,"y":0.0,"z":0.0}},{"classname":"env_spritetrail","origin":{"x":14350.0,"y":-4698.0,"z":-4521.0}},{"targetname":"beamerrotating10","classname":"momentary_rot_button","origin":{"x":14602.0,"y":-4699.0,"z":-4521.0},"angles":{"x":0.0,"y":0.0,"z":0.0}},{"classname":"env_spritetrail","origin":{"x":14622.0,"y":-4699.0,"z":-4521.0}},{"classname":"env_spritetrail","origin":{"x":14582.0,"y":-4699.0,"z":-4521.0}},{"classname":"env_spritetrail","origin":{"x":9896.0,"y":8284.0,"z":999.0}},{"targetname":"beamerrotating12","classname":"momentary_rot_button","origin":{"x":9876.04,"y":8284.0,"z":999.0},"angles":{"x":0.0,"y":0.0,"z":0.0}},{"classname":"env_spritetrail","origin":{"x":9856.0,"y":8284.0,"z":999.0}},{"classname":"light","origin":{"x":9876.0,"y":5889.0,"z":882.0}},{"classname":"light","origin":{"x":14452.0,"y":5889.0,"z":882.0}},{"classname":"light","origin":{"x":13908.0,"y":7741.0,"z":882.0}},{"classname":"light","origin":{"x":12564.0,"y":7741.0,"z":882.03}},{"classname":"light","origin":{"x":11220.0,"y":7741.0,"z":882.0}},{"classname":"light","origin":{"x":8532.0,"y":7741.0,"z":882.0}},{"classname":"light","origin":{"x":7188.0,"y":7741.0,"z":882.0}},{"classname":"light","origin":{"x":5844.0,"y":7741.0,"z":882.03}},{"classname":"light","origin":{"x":5300.0,"y":5889.0,"z":882.03}},{"classname":"light","origin":{"x":5300.0,"y":3968.0,"z":-478.0}},{"classname":"light","origin":{"x":5300.0,"y":2056.0,"z":-1868.0}},{"classname":"light","origin":{"x":5300.0,"y":-572.0,"z":-1868.0}},{"classname":"light","origin":{"x":5300.0,"y":-1825.0,"z":-2075.0}},{"classname":"light","origin":{"x":5300.0,"y":-1825.0,"z":-2752.0}},{"classname":"light","origin":{"x":5300.0,"y":-3203.0,"z":-2837.0}},{"classname":"light","origin":{"x":14452.0,"y":-3204.0,"z":-2835.0}},{"classname":"light","origin":{"x":14452.0,"y":-572.0,"z":-1868.0}},{"classname":"light","origin":{"x":14452.0,"y":2056.0,"z":-1868.0}},{"classname":"light","origin":{"x":14452.0,"y":3968.0,"z":-478.0}},{"classname":"trigger_multiple","origin":{"x":9876.0,"y":-2691.0,"z":3154.0}},{"classname":"light","origin":{"x":-8965.0,"y":6544.0,"z":6727.0}},{"classname":"light","origin":{"x":-8965.0,"y":6544.0,"z":5603.0}},{"classname":"light","origin":{"x":-8965.0,"y":6544.0,"z":4483.0}},{"targetname":"ctfilter","classname":"filter_activator_team","origin":{"x":5012.0,"y":-4707.0,"z":-4520.0}},{"targetname":"tfilter","classname":"filter_activator_team","origin":{"x":5012.0,"y":-4723.0,"z":-4520.0}},{"classname":"trigger_teleport","origin":{"x":-10405.0,"y":-6838.0,"z":-3449.0}},{"classname":"point_spotlight","origin":{"x":9202.1,"y":-2169.97,"z":3587.0},"angles":{"x":70.0,"y":90.0,"z":180.0}},{"classname":"point_spotlight","origin":{"x":9329.1,"y":-2169.97,"z":3587.0},"angles":{"x":70.0,"y":90.0,"z":180.0}},{"classname":"point_spotlight","origin":{"x":9456.1,"y":-2169.97,"z":3587.0},"angles":{"x":70.0,"y":90.0,"z":-180.0}},{"classname":"point_spotlight","origin":{"x":9710.11,"y":-2169.94,"z":3587.0},"angles":{"x":70.0,"y":90.0,"z":180.0}},{"classname":"point_spotlight","origin":{"x":9583.11,"y":-2169.94,"z":3587.0},"angles":{"x":70.0,"y":90.0,"z":-180.0}},{"classname":"point_spotlight","origin":{"x":10169.1,"y":-2162.97,"z":3587.0},"angles":{"x":70.0,"y":90.0,"z":-180.0}},{"classname":"point_spotlight","origin":{"x":10423.1,"y":-2162.94,"z":3587.0},"angles":{"x":70.0,"y":90.0,"z":180.0}},{"classname":"point_spotlight","origin":{"x":10042.1,"y":-2162.97,"z":3587.0},"angles":{"x":70.0,"y":90.0,"z":-180.0}},{"classname":"point_spotlight","origin":{"x":10296.1,"y":-2162.97,"z":3587.0},"angles":{"x":70.0,"y":90.0,"z":180.0}},{"classname":"point_spotlight","origin":{"x":10550.1,"y":-2162.94,"z":3587.0},"angles":{"x":70.0,"y":90.0,"z":-180.0}},{"classname":"trigger_teleport","origin":{"x":9876.0,"y":-8020.0,"z":-3664.5}},{"classname":"trigger_teleport","origin":{"x":-3691.5,"y":-11585.0,"z":-5072.5}},{"classname":"trigger_teleport","origin":{"x":-5193.0,"y":6774.0,"z":3943.5}},{"classname":"trigger_teleport","origin":{"x":-21.0,"y":2622.0,"z":2311.0}},{"classname":"trigger_teleport","origin":{"x":-2673.5,"y":5963.5,"z":803.5}},{"classname":"point_spotlight","origin":{"x":9876.0,"y":-3027.0,"z":3587.0},"angles":{"x":70.0,"y":90.0,"z":90.0}},{"classname":"point_spotlight","origin":{"x":9876.0,"y":-2859.0,"z":3587.0},"angles":{"x":70.0,"y":90.0,"z":90.0}},{"classname":"point_spotlight","origin":{"x":9876.11,"y":-2522.98,"z":3587.0},"angles":{"x":70.0,"y":90.0,"z":90.0}},{"classname":"point_spotlight","origin":{"x":9876.11,"y":-2690.98,"z":3587.0},"angles":{"x":70.0,"y":90.0,"z":90.0}},{"classname":"point_spotlight","origin":{"x":9876.0,"y":-2355.0,"z":3587.0},"angles":{"x":70.0,"y":90.0,"z":90.0}},{"classname":"point_spotlight","origin":{"x":9876.0,"y":-2187.0,"z":3587.0},"angles":{"x":70.0,"y":90.0,"z":90.0}},{"targetname":"dmgFilter1","classname":"filter_damage_type","origin":{"x":10228.6,"y":-2184.0,"z":3220.0}},{"targetname":"rotate_relay","classname":"logic_relay","origin":{"x":8606.0,"y":-8996.27,"z":4526.93}},{"classname":"trigger_teleport","origin":{"x":14460.0,"y":317.0,"z":-2769.0}},{"classname":"trigger_teleport","origin":{"x":9876.0,"y":7105.0,"z":-833.0}},{"classname":"trigger_teleport","origin":{"x":5300.0,"y":317.0,"z":-2769.0}},{"classname":"trigger_teleport","origin":{"x":9876.0,"y":1333.0,"z":-833.5}},{"classname":"trigger_multiple","origin":{"x":8512.5,"y":-9269.5,"z":4604.5}},{"classname":"trigger_teleport","origin":{"x":8632.0,"y":-14148.0,"z":-1333.0}},{"targetname":"Stage2.1","classname":"info_teleport_destination","origin":{"x":-9146.0,"y":7901.0,"z":7084.0},"angles":{"x":0.0,"y":315.0,"z":0.0}},{"targetname":"Stage2.2","classname":"info_teleport_destination","origin":{"x":-9143.0,"y":6057.0,"z":7084.0},"angles":{"x":0.0,"y":45.0,"z":0.0}},{"targetname":"stage3_end","classname":"trigger_multiple","origin":{"x":8512.5,"y":-8549.5,"z":4604.5}},{"targetname":"stage3_start","classname":"trigger_multiple","origin":{"x":9876.0,"y":-3740.0,"z":3315.0}},{"targetname":"stage1_start","classname":"trigger_multiple","origin":{"x":9876.0,"y":-2621.47,"z":3519.5}},{"targetname":"stage2_start","classname":"trigger_multiple","origin":{"x":-9108.0,"y":7865.5,"z":7070.5}},{"classname":"trigger_teleport","origin":{"x":-8909.0,"y":6112.0,"z":7022.5}},{"classname":"trigger_teleport","origin":{"x":-9033.0,"y":7792.0,"z":7022.5}},{"classname":"trigger_teleport","origin":{"x":2840.5,"y":-8549.5,"z":-6095.5}},{"classname":"trigger_teleport","origin":{"x":1978.5,"y":-8549.5,"z":-2285.5}},{"targetname":"stage2_start","classname":"trigger_multiple","origin":{"x":-9106.5,"y":6089.0,"z":7074.5}},{"classname":"trigger_teleport","origin":{"x":-9147.0,"y":7898.0,"z":7120.0}},{"targetname":"pushfilterNEW","classname":"filter_activator_name","origin":{"x":-8980.0,"y":7963.0,"z":6992.0}},{"classname":"trigger_teleport","origin":{"x":-9147.0,"y":6058.0,"z":7120.0}},{"classname":"trigger_teleport","origin":{"x":5164.0,"y":-4698.0,"z":-4499.0}},{"classname":"trigger_teleport","origin":{"x":5164.0,"y":-4698.0,"z":-4519.0}},{"classname":"trigger_teleport","origin":{"x":14330.0,"y":-4698.0,"z":-4499.0}},{"classname":"trigger_teleport","origin":{"x":14330.0,"y":-4698.0,"z":-4519.0}},{"targetname":"stage1_start","classname":"trigger_multiple","origin":{"x":9880.0,"y":-2683.97,"z":3208.0}},{"model":69,"clusters":[957],"classname":"func_brush","origin":{"x":-10405.0,"y":-6838.0,"z":-6281.0}},{"model":70,"clusters":[150,153,154,157,160,161,162,163,164,165,167,168,174],"classname":"func_brush","origin":{"x":9876.0,"y":-2181.27,"z":3470.0}},{"model":0,"vertLighting":0,"flags":0,"clusters":[789,788],"classname":"prop_static","origin":{"x":-9160.5,"y":6035.8,"z":7178.08},"angles":{"x":0.0,"y":45.0,"z":0.0}},{"model":0,"vertLighting":1,"flags":0,"clusters":[769,768],"classname":"prop_static","origin":{"x":-9160.5,"y":7919.5,"z":7178.08},"angles":{"x":0.0,"y":315.0,"z":0.0}}]}