{"name":"surf_crownroyal","lightmapUrl":"https://raw.githubusercontent.com/RSCSurf/SurfMaps1/main/maps/surf_crownroyal/lightmap.json?v=2048-992f","leafPages":[{"first":0,"count":5337,"url":"https://raw.githubusercontent.com/RSCSurf/SurfMaps1/main/maps/surf_crownroyal/geom/leafpage0.json?v=2048-992f"}],"dispPages":[{"first":0,"count":0,"url":"https://raw.githubusercontent.com/RSCSurf/SurfMaps1/main/maps/surf_crownroyal/geom/disppage0.json?v=2048-992f"}],"materialPages":[{"first":0,"count":14,"url":"https://raw.githubusercontent.com/RSCSurf/SurfMaps1/main/maps/surf_crownroyal/materials/matpage0.json?v=2048-992f"}],"brushModelPages":[{"first":0,"count":28,"url":"https://raw.githubusercontent.com/RSCSurf/SurfMaps1/main/maps/surf_crownroyal/geom/bsppage0.json?v=2048-992f"}],"studioModelPages":[{"first":0,"count":0,"url":"https://raw.githubusercontent.com/RSCSurf/SurfMaps1/main/maps/surf_crownroyal/geom/mdlpage0.json?v=2048-992f"}],"vertLightingPages":[{"first":0,"count":0,"url":"https://raw.githubusercontent.com/RSCSurf/SurfMaps1/main/maps/surf_crownroyal/geom/vhvpage0.json?v=2048-992f"}],"visPages":[{"first":0,"count":1789,"url":"https://raw.githubusercontent.com/RSCSurf/SurfMaps1/main/maps/surf_crownroyal/geom/vispage0.json?v=2048-992f"}],"ambientPages":[{"first":0,"count":4096,"url":"https://raw.githubusercontent.com/RSCSurf/SurfMaps1/main/maps/surf_crownroyal/geom/ambientpage0.json?v=2048-992f"},{"first":4096,"count":1241,"url":"https://raw.githubusercontent.com/RSCSurf/SurfMaps1/main/maps/surf_crownroyal/geom/ambientpage1.json?v=2048-992f"}],"entities":[{"skyMaterial":{"shader":"SourceUtils.Shaders.Sky","properties":[{"name":"cullFace","type":1,"value":false},{"name":"facePosX","type":4,"value":"https://raw.githubusercontent.com/RSCSurf/SurfMaps1/main/materials/skybox/cs_tibetrt.vtf.json?v=2048-992f"},{"name":"faceNegX","type":4,"value":"https://raw.githubusercontent.com/RSCSurf/SurfMaps1/main/materials/skybox/cs_tibetlf.vtf.json?v=2048-992f"},{"name":"facePosY","type":4,"value":"https://raw.githubusercontent.com/RSCSurf/SurfMaps1/main/materials/skybox/cs_tibetbk.vtf.json?v=2048-992f"},{"name":"faceNegY","type":4,"value":"https://raw.githubusercontent.com/RSCSurf/SurfMaps1/main/materials/skybox/cs_tibetft.vtf.json?v=2048-992f"},{"name":"facePosZ","type":4,"value":"https://raw.githubusercontent.com/RSCSurf/SurfMaps1/main/materials/skybox/cs_tibetup.vtf.json?v=2048-992f"},{"name":"faceNegZ","type":4,"value":"https://raw.githubusercontent.com/RSCSurf/SurfMaps1/main/materials/skybox/cs_tibetdn.vtf.json?v=2048-992f"}]},"model":0,"classname":"worldspawn"},{"classname":"light","origin":{"x":512.0,"y":-7744.0,"z":6240.0}},{"classname":"light","origin":{"x":-512.0,"y":-7744.0,"z":6240.0}},{"classname":"light","origin":{"x":1536.0,"y":-7744.0,"z":6240.0}},{"classname":"light","origin":{"x":9728.0,"y":-3968.0,"z":7680.0}},{"classname":"light","origin":{"x":8064.0,"y":-5312.0,"z":7680.0}},{"classname":"light","origin":{"x":11392.0,"y":-5312.0,"z":7680.0}},{"classname":"light","origin":{"x":11424.0,"y":-8416.0,"z":6400.0}},{"classname":"light","origin":{"x":8032.0,"y":-8416.0,"z":6400.0}},{"classname":"light","origin":{"x":9728.0,"y":-9760.0,"z":5888.0}},{"classname":"light","origin":{"x":9728.0,"y":-11008.0,"z":5632.0}},{"classname":"light","origin":{"x":9728.0,"y":-13760.0,"z":5632.0}},{"classname":"light","origin":{"x":8192.0,"y":-13568.0,"z":5632.0}},{"classname":"light","origin":{"x":11264.0,"y":-13568.0,"z":5632.0}},{"classname":"light","origin":{"x":9760.0,"y":-13824.0,"z":7424.0}},{"targetname":"bonus3","classname":"info_teleport_destination","origin":{"x":9728.0,"y":-12096.0,"z":9889.0},"angles":{"x":0.0,"y":90.0,"z":0.0}},{"targetname":"bonus2","classname":"info_teleport_destination","origin":{"x":512.0,"y":-9984.0,"z":8352.0},"angles":{"x":0.0,"y":90.0,"z":0.0}},{"targetname":"bonus1","classname":"info_teleport_destination","origin":{"x":-8704.0,"y":-8224.0,"z":9580.0},"angles":{"x":0.0,"y":270.0,"z":0.0}},{"classname":"trigger_teleport","origin":{"x":-8704.0,"y":-9472.0,"z":5140.0}},{"classname":"trigger_teleport","origin":{"x":480.0,"y":-9808.0,"z":6034.0}},{"classname":"trigger_teleport","origin":{"x":9728.0,"y":-9216.0,"z":6652.0}},{"targetname":"mapstart","classname":"trigger_multiple","origin":{"x":-8704.0,"y":2848.0,"z":272.0}},{"targetname":"stage2start","classname":"trigger_multiple","origin":{"x":-5504.0,"y":2848.0,"z":272.0}},{"targetname":"stage3start","classname":"trigger_multiple","origin":{"x":-1024.0,"y":2848.0,"z":272.0}},{"targetname":"stage4start","classname":"trigger_multiple","origin":{"x":6272.0,"y":2848.0,"z":272.0}},{"targetname":"stage5start","classname":"trigger_multiple","origin":{"x":12800.0,"y":3104.0,"z":272.0}},{"targetname":"mapend","classname":"trigger_multiple","origin":{"x":12800.0,"y":4352.0,"z":-6208.0}},{"targetname":"b3start","classname":"trigger_multiple","origin":{"x":9728.0,"y":-12096.0,"z":9856.0}},{"targetname":"b3end","classname":"trigger_multiple","origin":{"x":9760.0,"y":-12928.0,"z":7424.0}},{"targetname":"b2start","classname":"trigger_multiple","origin":{"x":512.0,"y":-9988.0,"z":8320.0}},{"targetname":"b2end","classname":"trigger_multiple","origin":{"x":512.0,"y":-12320.0,"z":5840.0}},{"targetname":"b1start","classname":"trigger_multiple","origin":{"x":-8704.0,"y":-8224.0,"z":9574.5}},{"targetname":"b1end","classname":"trigger_multiple","origin":{"x":-8704.0,"y":-5888.0,"z":3328.0}},{"classname":"light","origin":{"x":512.0,"y":-10752.0,"z":5952.0}},{"classname":"light","origin":{"x":512.0,"y":-9152.0,"z":5952.0}},{"classname":"light","origin":{"x":-8704.0,"y":-11392.0,"z":7424.0}},{"classname":"light","origin":{"x":-6656.0,"y":-11328.0,"z":7104.0}},{"classname":"light","origin":{"x":-10688.0,"y":-11392.0,"z":7104.0}},{"classname":"light","origin":{"x":-11904.0,"y":-10496.0,"z":6848.0}},{"classname":"light","origin":{"x":-5504.0,"y":-10496.0,"z":6848.0}},{"classname":"light","origin":{"x":-13312.0,"y":-9472.0,"z":6272.0}},{"classname":"light","origin":{"x":-4096.0,"y":-9472.0,"z":6272.0}},{"classname":"light","origin":{"x":-12800.0,"y":-8384.0,"z":5559.78}},{"classname":"light","origin":{"x":-4608.0,"y":-8384.0,"z":5559.78}},{"classname":"light","origin":{"x":-6720.0,"y":-9536.0,"z":4672.0}},{"classname":"light","origin":{"x":-10688.0,"y":-9536.0,"z":4672.0}},{"classname":"light","origin":{"x":-8704.0,"y":-9536.0,"z":4672.0}},{"classname":"light","origin":{"x":-8704.0,"y":-11968.0,"z":3648.0}},{"classname":"light","origin":{"x":-8704.0,"y":-9728.0,"z":3264.0}},{"classname":"light","origin":{"x":-8704.0,"y":-7680.0,"z":3264.0}},{"classname":"info_player_start","origin":{"x":-8704.0,"y":4256.0,"z":96.0},"angles":{"x":0.0,"y":270.0,"z":0.0}},{"classname":"info_player_terrorist","origin":{"x":-8768.0,"y":4256.0,"z":97.0},"angles":{"x":0.0,"y":270.0,"z":0.0}},{"classname":"info_player_counterterrorist","origin":{"x":-8640.0,"y":4256.0,"z":97.0},"angles":{"x":0.0,"y":270.0,"z":0.0}},{"classname":"trigger_teleport","origin":{"x":-8432.0,"y":4000.0,"z":176.0}},{"classname":"trigger_teleport","origin":{"x":-8432.0,"y":3744.0,"z":176.0}},{"classname":"trigger_teleport","origin":{"x":-8432.0,"y":3488.0,"z":176.0}},{"classname":"light","origin":{"x":-8704.0,"y":-8544.0,"z":8576.0}},{"classname":"light","origin":{"x":-8704.0,"y":-8544.0,"z":8576.0}},{"classname":"light","origin":{"x":-8704.0,"y":-8544.0,"z":8576.0}},{"classname":"light","origin":{"x":-8704.0,"y":-8544.0,"z":8576.0}},{"classname":"trigger_teleport","origin":{"x":12800.0,"y":480.0,"z":-2592.0}},{"classname":"trigger_teleport","origin":{"x":-5504.0,"y":-2176.0,"z":-1502.0}},{"classname":"trigger_teleport","origin":{"x":-8704.0,"y":-992.0,"z":-958.0}},{"classname":"trigger_teleport","origin":{"x":-1024.0,"y":256.0,"z":-1536.0}},{"classname":"trigger_teleport","origin":{"x":-5504.0,"y":-4544.0,"z":-1024.0}},{"classname":"trigger_teleport","origin":{"x":-8704.0,"y":-4352.0,"z":-576.0}},{"classname":"trigger_teleport","origin":{"x":6272.0,"y":-2304.0,"z":-3776.0}},{"classname":"trigger_teleport","origin":{"x":6272.0,"y":192.0,"z":-2830.0}},{"classname":"light","origin":{"x":14080.0,"y":3072.0,"z":-6656.0}},{"classname":"light","origin":{"x":12800.0,"y":3072.0,"z":-6656.0}},{"classname":"light","origin":{"x":11520.0,"y":3072.0,"z":-6656.0}},{"classname":"trigger_teleport","origin":{"x":-1024.0,"y":1088.0,"z":-2014.0}},{"classname":"light","origin":{"x":12800.0,"y":-512.0,"z":-448.0}},{"classname":"light","origin":{"x":11840.0,"y":-512.0,"z":-448.0}},{"classname":"light","origin":{"x":13760.0,"y":-512.0,"z":-448.0}},{"classname":"light","origin":{"x":14528.0,"y":-512.0,"z":-448.0}},{"classname":"light","origin":{"x":14528.0,"y":1056.0,"z":-448.0}},{"classname":"light","origin":{"x":11072.0,"y":1056.0,"z":-448.0}},{"classname":"light","origin":{"x":11072.0,"y":-512.0,"z":-448.0}},{"classname":"light","origin":{"x":11072.0,"y":3264.0,"z":-448.0}},{"classname":"light","origin":{"x":14528.0,"y":3264.0,"z":-448.0}},{"classname":"light","origin":{"x":12800.0,"y":3712.0,"z":-960.0}},{"classname":"light","origin":{"x":12800.0,"y":2816.0,"z":-2272.0}},{"classname":"light","origin":{"x":11072.0,"y":2816.0,"z":-2272.0}},{"classname":"light","origin":{"x":14528.0,"y":2816.0,"z":-2272.0}},{"classname":"light","origin":{"x":14528.0,"y":1792.0,"z":-2272.0}},{"classname":"light","origin":{"x":12800.0,"y":1792.0,"z":-2272.0}},{"classname":"light","origin":{"x":11072.0,"y":1792.0,"z":-2272.0}},{"classname":"light","origin":{"x":14528.0,"y":-1024.0,"z":-2272.0}},{"classname":"light","origin":{"x":12800.0,"y":-1024.0,"z":-2272.0}},{"classname":"light","origin":{"x":11072.0,"y":-1024.0,"z":-2272.0}},{"classname":"light","origin":{"x":12800.0,"y":-1792.0,"z":-2272.0}},{"classname":"light","origin":{"x":12800.0,"y":-2912.0,"z":-2272.0}},{"classname":"light","origin":{"x":12800.0,"y":-2912.0,"z":-3456.0}},{"classname":"light","origin":{"x":12800.0,"y":-2912.0,"z":-4224.0}},{"classname":"light","origin":{"x":12800.0,"y":-2912.0,"z":-5056.0}},{"classname":"light","origin":{"x":12800.0,"y":-2912.0,"z":-5824.0}},{"classname":"light","origin":{"x":6656.0,"y":-1024.0,"z":-3744.0}},{"classname":"light","origin":{"x":7648.0,"y":-32.0,"z":-3744.0}},{"classname":"light","origin":{"x":5664.0,"y":-32.0,"z":-3744.0}},{"classname":"light","origin":{"x":6656.0,"y":1024.0,"z":-3584.0}},{"classname":"light","origin":{"x":6656.0,"y":3072.0,"z":-3584.0}},{"classname":"light","origin":{"x":5088.0,"y":3968.0,"z":-4000.0}},{"classname":"light","origin":{"x":8224.0,"y":4224.0,"z":-4000.0}},{"classname":"light","origin":{"x":3936.0,"y":3584.0,"z":-4000.0}},{"classname":"light","origin":{"x":9376.0,"y":3584.0,"z":-4000.0}},{"classname":"light","origin":{"x":3936.0,"y":512.0,"z":-4000.0}},{"classname":"light","origin":{"x":9376.0,"y":512.0,"z":-4000.0}},{"classname":"light","origin":{"x":3936.0,"y":-2048.0,"z":-4000.0}},{"classname":"light","origin":{"x":9376.0,"y":-2048.0,"z":-4000.0}},{"classname":"light","origin":{"x":6656.0,"y":-2816.0,"z":-3328.0}},{"classname":"light","origin":{"x":12800.0,"y":-1536.0,"z":-7168.0}},{"classname":"light","origin":{"x":14080.0,"y":-1536.0,"z":-7168.0}},{"classname":"light","origin":{"x":11520.0,"y":-1536.0,"z":-7168.0}},{"classname":"light","origin":{"x":11520.0,"y":1024.0,"z":-7168.0}},{"classname":"light","origin":{"x":12800.0,"y":1024.0,"z":-7168.0}},{"classname":"light","origin":{"x":14080.0,"y":1024.0,"z":-7168.0}},{"classname":"light","origin":{"x":-3200.0,"y":1280.0,"z":-1023.0}},{"classname":"light","origin":{"x":1152.0,"y":1280.0,"z":-1023.0}},{"classname":"light","origin":{"x":-1024.0,"y":2560.0,"z":-1728.0}},{"classname":"light","origin":{"x":-2624.0,"y":2560.0,"z":-1728.0}},{"classname":"light","origin":{"x":576.0,"y":2560.0,"z":-1728.0}},{"classname":"light","origin":{"x":-1024.0,"y":1024.0,"z":-1728.0}},{"classname":"light","origin":{"x":-3200.0,"y":-384.0,"z":-1023.0}},{"classname":"light","origin":{"x":1152.0,"y":-384.0,"z":-1023.0}},{"classname":"light","origin":{"x":6656.0,"y":-3904.0,"z":-3328.0}},{"targetname":"stage5","classname":"info_teleport_destination","origin":{"x":12800.0,"y":3104.0,"z":225.0},"angles":{"x":0.0,"y":270.0,"z":0.0}},{"targetname":"stage1","classname":"info_teleport_destination","origin":{"x":-8704.0,"y":2848.0,"z":225.0},"angles":{"x":0.0,"y":270.0,"z":0.0}},{"Brightness":{"R":239,"G":235,"B":186,"A":219},"Ambient":{"R":142,"G":166,"B":176,"A":225},"BrightnessHdr":{"R":171,"G":0,"B":0,"A":255},"AmbientHdr":{"R":239,"G":235,"B":186,"A":10},"BrightnessScaleHdr":0.0,"AmbientScaleHdr":1.0,"Pitch":-35.0,"classname":"light_environment","origin":{"x":-8704.0,"y":2848.0,"z":160.0},"angles":{"x":0.0,"y":153.0,"z":0.0}},{"targetname":"stage2","classname":"info_teleport_destination","origin":{"x":-5504.0,"y":2848.0,"z":225.0},"angles":{"x":0.0,"y":270.0,"z":0.0}},{"targetname":"stage3","classname":"info_teleport_destination","origin":{"x":-1024.0,"y":2848.0,"z":225.0},"angles":{"x":0.0,"y":270.0,"z":0.0}},{"targetname":"stage4","classname":"info_teleport_destination","origin":{"x":6272.0,"y":2848.0,"z":225.0},"angles":{"x":0.0,"y":270.0,"z":0.0}}]}