{"name":"surf_corner","lightmapUrl":"https://raw.githubusercontent.com/RSCSurf/SurfMaps1/main/maps/surf_corner/lightmap.json?v=2048-96bd","leafPages":[{"first":0,"count":825,"url":"https://raw.githubusercontent.com/RSCSurf/SurfMaps1/main/maps/surf_corner/geom/leafpage0.json?v=2048-96bd"}],"dispPages":[{"first":0,"count":0,"url":"https://raw.githubusercontent.com/RSCSurf/SurfMaps1/main/maps/surf_corner/geom/disppage0.json?v=2048-96bd"}],"materialPages":[{"first":0,"count":26,"url":"https://raw.githubusercontent.com/RSCSurf/SurfMaps1/main/maps/surf_corner/materials/matpage0.json?v=2048-96bd"}],"brushModelPages":[{"first":0,"count":17,"url":"https://raw.githubusercontent.com/RSCSurf/SurfMaps1/main/maps/surf_corner/geom/bsppage0.json?v=2048-96bd"}],"studioModelPages":[{"first":0,"count":0,"url":"https://raw.githubusercontent.com/RSCSurf/SurfMaps1/main/maps/surf_corner/geom/mdlpage0.json?v=2048-96bd"}],"vertLightingPages":[{"first":0,"count":0,"url":"https://raw.githubusercontent.com/RSCSurf/SurfMaps1/main/maps/surf_corner/geom/vhvpage0.json?v=2048-96bd"}],"visPages":[{"first":0,"count":277,"url":"https://raw.githubusercontent.com/RSCSurf/SurfMaps1/main/maps/surf_corner/geom/vispage0.json?v=2048-96bd"}],"ambientPages":[{"first":0,"count":825,"url":"https://raw.githubusercontent.com/RSCSurf/SurfMaps1/main/maps/surf_corner/geom/ambientpage0.json?v=2048-96bd"}],"entities":[{"skyMaterial":{"shader":"SourceUtils.Shaders.Sky","properties":[{"name":"cullFace","type":1,"value":false},{"name":"facePosX","type":4,"value":"https://raw.githubusercontent.com/RSCSurf/SurfMaps1/main/materials/skybox/vertigort.vtf.json?v=2048-96bd"},{"name":"faceNegX","type":4,"value":"https://raw.githubusercontent.com/RSCSurf/SurfMaps1/main/materials/skybox/vertigolf.vtf.json?v=2048-96bd"},{"name":"facePosY","type":4,"value":"https://raw.githubusercontent.com/RSCSurf/SurfMaps1/main/materials/skybox/vertigobk.vtf.json?v=2048-96bd"},{"name":"faceNegY","type":4,"value":"https://raw.githubusercontent.com/RSCSurf/SurfMaps1/main/materials/skybox/vertigoft.vtf.json?v=2048-96bd"},{"name":"facePosZ","type":4,"value":"https://raw.githubusercontent.com/RSCSurf/SurfMaps1/main/materials/skybox/vertigoup.vtf.json?v=2048-96bd"},{"name":"faceNegZ","type":4,"value":"https://raw.githubusercontent.com/RSCSurf/SurfMaps1/main/materials/skybox/vertigodn.vtf.json?v=2048-96bd"}]},"model":0,"classname":"worldspawn"},{"targetname":"Stage5","classname":"info_teleport_destination","origin":{"x":-1696.0,"y":-4192.0,"z":-224.0},"angles":{"x":0.0,"y":180.0,"z":0.0}},{"classname":"trigger_teleport","origin":{"x":-5301.0,"y":-4208.0,"z":-352.0}},{"classname":"trigger_teleport","origin":{"x":-3455.99,"y":-4191.99,"z":-816.0}},{"targetname":"Stage6","classname":"info_teleport_destination","origin":{"x":-1632.0,"y":-5464.0,"z":121.553},"angles":{"x":0.0,"y":180.0,"z":0.0}},{"classname":"trigger_teleport","origin":{"x":-3391.99,"y":-6395.97,"z":-2736.0}},{"classname":"light","origin":{"x":-3737.49,"y":-5955.09,"z":-2084.71}},{"classname":"trigger_teleport","origin":{"x":-3413.25,"y":-6464.0,"z":-1264.0}},{"classname":"light_spot","origin":{"x":-5034.47,"y":-5248.0,"z":-2304.0},"angles":{"x":-90.0,"y":0.0,"z":0.0}},{"classname":"trigger_teleport","origin":{"x":-3520.0,"y":-3040.0,"z":-800.0}},{"classname":"trigger_teleport","origin":{"x":-5367.0,"y":-3088.0,"z":-397.46}},{"targetname":"Stage4","classname":"info_teleport_destination","origin":{"x":-1760.0,"y":-3072.0,"z":128.0},"angles":{"x":0.0,"y":180.0,"z":0.0}},{"classname":"trigger_teleport","origin":{"x":-1232.59,"y":-1975.33,"z":-1484.12}},{"classname":"trigger_teleport","origin":{"x":-1960.0,"y":-1976.58,"z":-1235.68}},{"classname":"trigger_teleport","origin":{"x":-3271.59,"y":-2016.01,"z":-1656.0}},{"classname":"light","origin":{"x":-1693.95,"y":-1979.07,"z":-873.0}},{"classname":"light","origin":{"x":-2035.75,"y":-2004.82,"z":-873.0}},{"classname":"light","origin":{"x":-3498.34,"y":-1982.32,"z":-873.0}},{"classname":"light","origin":{"x":-4456.8,"y":-1978.74,"z":-873.0}},{"targetname":"Stage2","classname":"info_teleport_destination","origin":{"x":-1696.0,"y":-992.0,"z":16.0},"angles":{"x":0.0,"y":180.0,"z":0.0}},{"classname":"trigger_teleport","origin":{"x":-5303.0,"y":-1040.0,"z":-397.46}},{"classname":"trigger_teleport","origin":{"x":-3456.0,"y":-992.0,"z":-816.0}},{"classname":"trigger_teleport","origin":{"x":-4720.0,"y":-1200.0,"z":-445.0}},{"classname":"trigger_teleport","origin":{"x":-3024.0,"y":-722.0,"z":-439.0}},{"targetname":"Stage3","classname":"info_teleport_destination","origin":{"x":-1319.59,"y":-1980.59,"z":-0.000747681},"angles":{"x":0.0,"y":180.0,"z":0.0}},{"classname":"trigger_teleport","origin":{"x":-3052.16,"y":-1976.58,"z":-816.0}},{"classname":"trigger_teleport","origin":{"x":-5303.0,"y":-16.0,"z":-432.0}},{"Brightness":{"R":255,"G":255,"B":255,"A":144},"Ambient":{"R":255,"G":255,"B":255,"A":50},"BrightnessHdr":{"R":255,"G":255,"B":255,"A":1},"AmbientHdr":{"R":255,"G":255,"B":255,"A":1},"BrightnessScaleHdr":1.0,"AmbientScaleHdr":1.0,"Pitch":-32.0,"classname":"light_environment","origin":{"x":-2048.0,"y":133.731,"z":192.0},"angles":{"x":0.0,"y":0.0,"z":0.0}},{"classname":"trigger_teleport","origin":{"x":-2624.0,"y":0.0,"z":-784.0}},{"classname":"info_player_terrorist","origin":{"x":4.13264,"y":120.0,"z":32.0},"angles":{"x":0.0,"y":180.0,"z":0.0}},{"targetname":"Stage1","classname":"info_teleport_destination","origin":{"x":0.0,"y":0.0,"z":32.0},"angles":{"x":0.0,"y":180.0,"z":0.0}},{"classname":"info_player_counterterrorist","origin":{"x":0.0,"y":-128.0,"z":32.0},"angles":{"x":0.0,"y":180.0,"z":0.0}},{"classname":"water_lod_control"}]}