{"name":"surf_canisius2_fix","lightmapUrl":"https://raw.githubusercontent.com/RSCSurf/SurfMaps1/main/maps/surf_canisius2_fix/lightmap.json?v=2048-627f","leafPages":[{"first":0,"count":6335,"url":"https://raw.githubusercontent.com/RSCSurf/SurfMaps1/main/maps/surf_canisius2_fix/geom/leafpage0.json?v=2048-627f"}],"dispPages":[{"first":0,"count":1,"url":"https://raw.githubusercontent.com/RSCSurf/SurfMaps1/main/maps/surf_canisius2_fix/geom/disppage0.json?v=2048-627f"}],"materialPages":[{"first":0,"count":21,"url":"https://raw.githubusercontent.com/RSCSurf/SurfMaps1/main/maps/surf_canisius2_fix/materials/matpage0.json?v=2048-627f"}],"brushModelPages":[{"first":0,"count":1,"url":"https://raw.githubusercontent.com/RSCSurf/SurfMaps1/main/maps/surf_canisius2_fix/geom/bsppage0.json?v=2048-627f"},{"first":1,"count":57,"url":"https://raw.githubusercontent.com/RSCSurf/SurfMaps1/main/maps/surf_canisius2_fix/geom/bsppage1.json?v=2048-627f"}],"studioModelPages":[{"first":0,"count":0,"url":"https://raw.githubusercontent.com/RSCSurf/SurfMaps1/main/maps/surf_canisius2_fix/geom/mdlpage0.json?v=2048-627f"}],"vertLightingPages":[{"first":0,"count":0,"url":"https://raw.githubusercontent.com/RSCSurf/SurfMaps1/main/maps/surf_canisius2_fix/geom/vhvpage0.json?v=2048-627f"}],"visPages":[{"first":0,"count":2180,"url":"https://raw.githubusercontent.com/RSCSurf/SurfMaps1/main/maps/surf_canisius2_fix/geom/vispage0.json?v=2048-627f"}],"ambientPages":[{"first":0,"count":4096,"url":"https://raw.githubusercontent.com/RSCSurf/SurfMaps1/main/maps/surf_canisius2_fix/geom/ambientpage0.json?v=2048-627f"},{"first":4096,"count":2239,"url":"https://raw.githubusercontent.com/RSCSurf/SurfMaps1/main/maps/surf_canisius2_fix/geom/ambientpage1.json?v=2048-627f"}],"entities":[{"skyMaterial":{"shader":"SourceUtils.Shaders.Sky","properties":[{"name":"cullFace","type":1,"value":false},{"name":"facePosX","type":4,"value":"https://raw.githubusercontent.com/RSCSurf/SurfMaps1/main/maps/surf_canisius2_fix/materials/skybox/purplebeachrt.vtf.json?v=2048-627f"},{"name":"faceNegX","type":4,"value":"https://raw.githubusercontent.com/RSCSurf/SurfMaps1/main/maps/surf_canisius2_fix/materials/skybox/purplebeachlf.vtf.json?v=2048-627f"},{"name":"facePosY","type":4,"value":"https://raw.githubusercontent.com/RSCSurf/SurfMaps1/main/maps/surf_canisius2_fix/materials/skybox/purplebeachbk.vtf.json?v=2048-627f"},{"name":"faceNegY","type":4,"value":"https://raw.githubusercontent.com/RSCSurf/SurfMaps1/main/maps/surf_canisius2_fix/materials/skybox/purplebeachft.vtf.json?v=2048-627f"},{"name":"facePosZ","type":4,"value":"https://raw.githubusercontent.com/RSCSurf/SurfMaps1/main/maps/surf_canisius2_fix/materials/skybox/purplebeachup.vtf.json?v=2048-627f"},{"name":"faceNegZ","type":4,"value":"https://raw.githubusercontent.com/RSCSurf/SurfMaps1/main/maps/surf_canisius2_fix/materials/skybox/purplebeachdn.vtf.json?v=2048-627f"}]},"model":0,"classname":"worldspawn"},{"targetname":"wall_laz1","classname":"info_target","origin":{"x":-8333.5,"y":8131.0,"z":380.5},"angles":{"x":0.0,"y":0.0,"z":0.0}},{"targetname":"laz1","classname":"env_beam","origin":{"x":-10701.5,"y":8131.0,"z":380.5}},{"targetname":"wall_laz2","classname":"info_target","origin":{"x":-8493.5,"y":8131.0,"z":268.5},"angles":{"x":0.0,"y":0.0,"z":0.0}},{"targetname":"laz2","classname":"env_beam","origin":{"x":-10541.5,"y":8131.0,"z":268.5}},{"targetname":"wall_laz3","classname":"info_target","origin":{"x":-8333.5,"y":7091.0,"z":380.5},"angles":{"x":0.0,"y":0.0,"z":0.0}},{"targetname":"laz3","classname":"env_beam","origin":{"x":-10701.5,"y":7091.0,"z":380.5}},{"targetname":"wall_laz4","classname":"info_target","origin":{"x":-8493.5,"y":7091.0,"z":268.5},"angles":{"x":0.0,"y":0.0,"z":0.0}},{"targetname":"laz4","classname":"env_beam","origin":{"x":-10541.5,"y":7091.0,"z":268.5}},{"targetname":"wall_laz6","classname":"info_target","origin":{"x":-10805.5,"y":7867.0,"z":268.5},"angles":{"x":0.0,"y":0.0,"z":0.0}},{"targetname":"laz6","classname":"env_beam","origin":{"x":-10805.5,"y":7355.0,"z":268.5}},{"targetname":"wall_laz5","classname":"info_target","origin":{"x":-10805.5,"y":8027.0,"z":380.5},"angles":{"x":0.0,"y":0.0,"z":0.0}},{"targetname":"laz5","classname":"env_beam","origin":{"x":-10805.5,"y":7195.0,"z":380.5}},{"classname":"point_spotlight","origin":{"x":-10061.5,"y":7963.0,"z":-139.5},"angles":{"x":-90.0,"y":90.0,"z":0.0}},{"classname":"light_spot","origin":{"x":-10061.5,"y":7963.0,"z":-143.5},"angles":{"x":90.0,"y":180.0,"z":0.0}},{"classname":"point_spotlight","origin":{"x":-9149.5,"y":7963.0,"z":-139.5},"angles":{"x":-90.0,"y":90.0,"z":0.0}},{"classname":"light_spot","origin":{"x":-9149.5,"y":7963.0,"z":-143.5},"angles":{"x":90.0,"y":180.0,"z":0.0}},{"classname":"point_spotlight","origin":{"x":-8492.9,"y":7963.0,"z":-139.911},"angles":{"x":-90.0,"y":90.0,"z":0.0}},{"classname":"light_spot","origin":{"x":-8492.9,"y":7963.0,"z":-143.911},"angles":{"x":90.0,"y":180.0,"z":0.0}},{"classname":"point_spotlight","origin":{"x":-9149.5,"y":7259.0,"z":-139.5},"angles":{"x":-90.0,"y":90.0,"z":0.0}},{"classname":"light_spot","origin":{"x":-9149.5,"y":7259.0,"z":-143.5},"angles":{"x":90.0,"y":180.0,"z":0.0}},{"classname":"point_spotlight","origin":{"x":-8492.9,"y":7259.0,"z":-139.911},"angles":{"x":-90.0,"y":90.0,"z":0.0}},{"classname":"light_spot","origin":{"x":-8492.9,"y":7259.0,"z":-143.911},"angles":{"x":90.0,"y":180.0,"z":0.0}},{"classname":"point_spotlight","origin":{"x":-10061.5,"y":7259.0,"z":-139.5},"angles":{"x":-90.0,"y":90.0,"z":0.0}},{"classname":"light_spot","origin":{"x":-10061.5,"y":7259.0,"z":-143.5},"angles":{"x":90.0,"y":180.0,"z":0.0}},{"classname":"water_lod_control","origin":{"x":-4368.5,"y":1893.5,"z":-444.239}},{"targetname":"desty_stage2","classname":"info_teleport_destination","origin":{"x":-4368.5,"y":1954.5,"z":-257.239},"angles":{"x":0.0,"y":270.0,"z":0.0}},{"targetname":"dmgfilter_2","classname":"filter_damage_type","origin":{"x":-3929.5,"y":2044.5,"z":-459.348}},{"classname":"light","origin":{"x":-4368.5,"y":1893.5,"z":-312.239}},{"classname":"trigger_teleport","origin":{"x":-4369.0,"y":1953.5,"z":-208.0}},{"classname":"light","origin":{"x":-5168.5,"y":-394.5,"z":-1178.5}},{"classname":"light","origin":{"x":-5168.5,"y":261.5,"z":-1178.5}},{"classname":"light","origin":{"x":-5168.5,"y":917.5,"z":-1178.5}},{"classname":"light","origin":{"x":-5168.5,"y":1573.5,"z":-1178.5}},{"classname":"light","origin":{"x":-3568.17,"y":258.49,"z":-1178.5}},{"classname":"light","origin":{"x":-3568.17,"y":914.49,"z":-1178.5}},{"classname":"light","origin":{"x":-3568.17,"y":1570.49,"z":-1178.5}},{"classname":"point_spotlight","origin":{"x":-3568.5,"y":259.5,"z":-1716.5},"angles":{"x":-90.0,"y":0.0,"z":0.0}},{"classname":"light_spot","origin":{"x":-3568.5,"y":259.5,"z":-1720.5},"angles":{"x":90.0,"y":90.0,"z":0.0}},{"classname":"point_spotlight","origin":{"x":-3568.5,"y":915.5,"z":-1716.5},"angles":{"x":-90.0,"y":0.0,"z":0.0}},{"classname":"light_spot","origin":{"x":-3568.5,"y":915.5,"z":-1720.5},"angles":{"x":90.0,"y":90.0,"z":0.0}},{"classname":"point_spotlight","origin":{"x":-3568.5,"y":1573.5,"z":-1716.5},"angles":{"x":-90.0,"y":0.0,"z":0.0}},{"classname":"light_spot","origin":{"x":-3568.5,"y":1573.5,"z":-1720.5},"angles":{"x":90.0,"y":90.0,"z":0.0}},{"classname":"point_spotlight","origin":{"x":-5168.5,"y":259.5,"z":-1716.5},"angles":{"x":-90.0,"y":0.0,"z":0.0}},{"classname":"light_spot","origin":{"x":-5168.5,"y":259.5,"z":-1720.5},"angles":{"x":90.0,"y":90.0,"z":0.0}},{"classname":"point_spotlight","origin":{"x":-5168.5,"y":915.5,"z":-1716.5},"angles":{"x":-90.0,"y":0.0,"z":0.0}},{"classname":"light_spot","origin":{"x":-5168.5,"y":915.5,"z":-1720.5},"angles":{"x":90.0,"y":90.0,"z":0.0}},{"classname":"point_spotlight","origin":{"x":-5168.5,"y":1573.5,"z":-1716.5},"angles":{"x":-90.0,"y":0.0,"z":0.0}},{"classname":"light_spot","origin":{"x":-5168.5,"y":1573.5,"z":-1720.5},"angles":{"x":90.0,"y":90.0,"z":0.0}},{"classname":"light_spot","origin":{"x":-3568.5,"y":-396.93,"z":-1720.91},"angles":{"x":90.0,"y":90.0,"z":0.0}},{"classname":"point_spotlight","origin":{"x":-3568.5,"y":-396.93,"z":-1716.91},"angles":{"x":-90.0,"y":0.0,"z":0.0}},{"classname":"point_spotlight","origin":{"x":-3568.5,"y":-1052.93,"z":-1715.51},"angles":{"x":-90.0,"y":0.0,"z":0.0}},{"classname":"light_spot","origin":{"x":-3568.5,"y":-1052.93,"z":-1719.51},"angles":{"x":90.0,"y":90.0,"z":0.0}},{"classname":"light_spot","origin":{"x":-3568.5,"y":-1708.93,"z":-1720.91},"angles":{"x":90.0,"y":90.0,"z":0.0}},{"classname":"point_spotlight","origin":{"x":-3568.5,"y":-1708.93,"z":-1716.91},"angles":{"x":-90.0,"y":0.0,"z":0.0}},{"classname":"light_spot","origin":{"x":-5168.5,"y":-1708.93,"z":-1720.91},"angles":{"x":90.0,"y":90.0,"z":0.0}},{"classname":"point_spotlight","origin":{"x":-5168.5,"y":-1708.93,"z":-1716.91},"angles":{"x":-90.0,"y":0.0,"z":0.0}},{"classname":"point_spotlight","origin":{"x":-5168.5,"y":-1053.06,"z":-1715.51},"angles":{"x":-90.0,"y":0.0,"z":0.0}},{"classname":"light_spot","origin":{"x":-5168.5,"y":-1053.06,"z":-1719.51},"angles":{"x":90.0,"y":90.0,"z":0.0}},{"classname":"point_spotlight","origin":{"x":-5168.5,"y":-397.06,"z":-1716.91},"angles":{"x":-90.0,"y":0.0,"z":0.0}},{"classname":"light_spot","origin":{"x":-5168.5,"y":-397.06,"z":-1720.91},"angles":{"x":90.0,"y":90.0,"z":0.0}},{"classname":"point_spotlight","origin":{"x":-5168.5,"y":-617.5,"z":909.5},"angles":{"x":-90.0,"y":0.0,"z":0.0}},{"classname":"light_spot","origin":{"x":-5168.5,"y":-617.5,"z":905.5},"angles":{"x":90.0,"y":90.0,"z":0.0}},{"classname":"point_spotlight","origin":{"x":-3568.5,"y":-617.5,"z":909.5},"angles":{"x":-90.0,"y":0.0,"z":0.0}},{"classname":"light_spot","origin":{"x":-3568.5,"y":-617.5,"z":905.5},"angles":{"x":90.0,"y":90.0,"z":0.0}},{"classname":"point_spotlight","origin":{"x":-5168.5,"y":40.5,"z":909.5},"angles":{"x":-90.0,"y":0.0,"z":0.0}},{"classname":"light_spot","origin":{"x":-5168.5,"y":40.5,"z":905.5},"angles":{"x":90.0,"y":90.0,"z":0.0}},{"classname":"point_spotlight","origin":{"x":-3568.5,"y":40.5,"z":909.5},"angles":{"x":-90.0,"y":0.0,"z":0.0}},{"classname":"light_spot","origin":{"x":-3568.5,"y":40.5,"z":905.5},"angles":{"x":90.0,"y":90.0,"z":0.0}},{"classname":"point_spotlight","origin":{"x":-5168.5,"y":698.5,"z":909.5},"angles":{"x":-90.0,"y":0.0,"z":0.0}},{"classname":"light_spot","origin":{"x":-5168.5,"y":698.5,"z":905.5},"angles":{"x":90.0,"y":90.0,"z":0.0}},{"classname":"point_spotlight","origin":{"x":-3568.5,"y":698.5,"z":909.5},"angles":{"x":-90.0,"y":0.0,"z":0.0}},{"classname":"light_spot","origin":{"x":-3568.5,"y":698.5,"z":905.5},"angles":{"x":90.0,"y":90.0,"z":0.0}},{"classname":"point_spotlight","origin":{"x":-3568.5,"y":1356.5,"z":909.5},"angles":{"x":-90.0,"y":0.0,"z":0.0}},{"classname":"light_spot","origin":{"x":-3568.5,"y":1356.5,"z":905.5},"angles":{"x":90.0,"y":90.0,"z":0.0}},{"classname":"point_spotlight","origin":{"x":-3568.5,"y":2014.5,"z":909.5},"angles":{"x":-90.0,"y":0.0,"z":0.0}},{"classname":"light_spot","origin":{"x":-3568.5,"y":2014.5,"z":905.5},"angles":{"x":90.0,"y":90.0,"z":0.0}},{"classname":"point_spotlight","origin":{"x":-5168.5,"y":1356.5,"z":909.5},"angles":{"x":-90.0,"y":0.0,"z":0.0}},{"classname":"light_spot","origin":{"x":-5168.5,"y":1356.5,"z":905.5},"angles":{"x":90.0,"y":90.0,"z":0.0}},{"classname":"point_spotlight","origin":{"x":-5168.5,"y":2014.5,"z":909.5},"angles":{"x":-90.0,"y":0.0,"z":0.0}},{"classname":"light_spot","origin":{"x":-5168.5,"y":2014.5,"z":905.5},"angles":{"x":90.0,"y":90.0,"z":0.0}},{"classname":"point_spotlight","origin":{"x":-5168.5,"y":2672.5,"z":909.5},"angles":{"x":-90.0,"y":0.0,"z":0.0}},{"classname":"light_spot","origin":{"x":-5168.5,"y":2672.5,"z":905.5},"angles":{"x":90.0,"y":90.0,"z":0.0}},{"model":2,"clusters":[1341,1358,1375,1389,1415,1423,1425,1428,1434,1437,1440,1444,1447,1450,1453,1460,1462,1471,1475,1478,1481,1483,1487,1490,1493,1497,1499,1802,1823,1830,1841,1844,1965,1969,1977,1980,2038,2041],"classname":"func_brush","origin":{"x":-4368.5,"y":1356.5,"z":889.5}},{"classname":"point_spotlight","origin":{"x":-5168.5,"y":3330.5,"z":909.5},"angles":{"x":-90.0,"y":0.0,"z":0.0}},{"classname":"light_spot","origin":{"x":-5168.5,"y":3330.5,"z":905.5},"angles":{"x":90.0,"y":90.0,"z":0.0}},{"classname":"point_spotlight","origin":{"x":-3568.5,"y":3330.5,"z":909.5},"angles":{"x":-90.0,"y":0.0,"z":0.0}},{"classname":"light_spot","origin":{"x":-3568.5,"y":3330.5,"z":905.5},"angles":{"x":90.0,"y":90.0,"z":0.0}},{"classname":"point_spotlight","origin":{"x":-3568.5,"y":2672.5,"z":909.5},"angles":{"x":-90.0,"y":0.0,"z":0.0}},{"classname":"light_spot","origin":{"x":-3568.5,"y":2672.5,"z":905.5},"angles":{"x":90.0,"y":90.0,"z":0.0}},{"classname":"point_spotlight","origin":{"x":-5168.5,"y":3124.5,"z":-1225.5},"angles":{"x":-90.0,"y":0.0,"z":0.0}},{"classname":"light_spot","origin":{"x":-5168.5,"y":3124.5,"z":-1229.5},"angles":{"x":90.0,"y":90.0,"z":0.0}},{"classname":"point_spotlight","origin":{"x":-3568.5,"y":3782.5,"z":-1225.5},"angles":{"x":-90.0,"y":0.0,"z":0.0}},{"classname":"light_spot","origin":{"x":-3568.5,"y":3782.5,"z":-1229.5},"angles":{"x":90.0,"y":90.0,"z":0.0}},{"classname":"point_spotlight","origin":{"x":-5168.5,"y":3782.5,"z":-1225.5},"angles":{"x":-90.0,"y":0.0,"z":0.0}},{"classname":"light_spot","origin":{"x":-5168.5,"y":3782.5,"z":-1229.5},"angles":{"x":90.0,"y":90.0,"z":0.0}},{"classname":"point_spotlight","origin":{"x":-3568.5,"y":3124.5,"z":-1225.5},"angles":{"x":-90.0,"y":0.0,"z":0.0}},{"classname":"light_spot","origin":{"x":-3568.5,"y":3124.5,"z":-1229.5},"angles":{"x":90.0,"y":90.0,"z":0.0}},{"classname":"point_spotlight","origin":{"x":-3568.5,"y":2466.5,"z":-1225.5},"angles":{"x":-90.0,"y":0.0,"z":0.0}},{"classname":"light_spot","origin":{"x":-3568.5,"y":2466.5,"z":-1229.5},"angles":{"x":90.0,"y":90.0,"z":0.0}},{"classname":"point_spotlight","origin":{"x":-5168.5,"y":2466.5,"z":-1225.5},"angles":{"x":-90.0,"y":0.0,"z":0.0}},{"classname":"light_spot","origin":{"x":-5168.5,"y":2466.5,"z":-1229.5},"angles":{"x":90.0,"y":90.0,"z":0.0}},{"classname":"water_lod_control","origin":{"x":528.0,"y":4261.0,"z":2526.26}},{"targetname":"desty_stage3","classname":"info_teleport_destination","origin":{"x":528.0,"y":4322.0,"z":2713.26},"angles":{"x":0.0,"y":270.0,"z":0.0}},{"targetname":"dmgfilter_3","classname":"filter_damage_type","origin":{"x":967.0,"y":4412.0,"z":2511.15}},{"classname":"light","origin":{"x":528.0,"y":4261.0,"z":2658.26}},{"classname":"trigger_teleport","origin":{"x":527.5,"y":4321.0,"z":2760.0}},{"classname":"point_spotlight","origin":{"x":528.0,"y":3232.54,"z":918.81},"angles":{"x":-69.0,"y":270.0,"z":90.0}},{"classname":"light_spot","origin":{"x":528.0,"y":3233.97,"z":915.08},"angles":{"x":69.0,"y":270.0,"z":-180.0}},{"classname":"light_spot","origin":{"x":528.0,"y":3848.37,"z":1144.13},"angles":{"x":69.5,"y":270.0,"z":180.0}},{"classname":"point_spotlight","origin":{"x":528.0,"y":3846.96,"z":1147.88},"angles":{"x":-69.5,"y":270.0,"z":90.0}},{"classname":"point_spotlight","origin":{"x":528.0,"y":2551.0,"z":834.36},"angles":{"x":-90.0,"y":0.0,"z":0.0}},{"classname":"light_spot","origin":{"x":528.0,"y":2551.0,"z":830.36},"angles":{"x":90.0,"y":90.0,"z":0.0}},{"classname":"point_spotlight","origin":{"x":528.0,"y":1487.79,"z":267.81},"angles":{"x":-69.0,"y":270.0,"z":90.0}},{"classname":"light_spot","origin":{"x":528.0,"y":1489.22,"z":264.08},"angles":{"x":69.0,"y":270.0,"z":-180.0}},{"classname":"light","origin":{"x":528.0,"y":3056.0,"z":1809.29}},{"classname":"light","origin":{"x":528.0,"y":3679.89,"z":2012.0}},{"classname":"light","origin":{"x":528.0,"y":1841.11,"z":1441.28}},{"classname":"light","origin":{"x":528.0,"y":2465.0,"z":1644.0}},{"classname":"point_spotlight","origin":{"x":1336.0,"y":3241.0,"z":-1219.01},"angles":{"x":-90.0,"y":0.0,"z":0.0}},{"classname":"light_spot","origin":{"x":1336.0,"y":3241.0,"z":-1223.01},"angles":{"x":90.0,"y":90.0,"z":0.0}},{"classname":"point_spotlight","origin":{"x":-280.0,"y":3241.0,"z":-1219.01},"angles":{"x":-90.0,"y":0.0,"z":0.0}},{"classname":"light_spot","origin":{"x":-280.0,"y":3241.0,"z":-1223.01},"angles":{"x":90.0,"y":90.0,"z":0.0}},{"classname":"point_spotlight","origin":{"x":1336.0,"y":2419.0,"z":-1219.0},"angles":{"x":-90.0,"y":0.0,"z":0.0}},{"classname":"light_spot","origin":{"x":1336.0,"y":2419.0,"z":-1223.0},"angles":{"x":90.0,"y":90.0,"z":0.0}},{"classname":"point_spotlight","origin":{"x":-280.0,"y":2419.0,"z":-1219.0},"angles":{"x":-90.0,"y":0.0,"z":0.0}},{"classname":"light_spot","origin":{"x":-280.0,"y":2419.0,"z":-1223.0},"angles":{"x":90.0,"y":90.0,"z":0.0}},{"classname":"point_spotlight","origin":{"x":1336.0,"y":1597.0,"z":-1219.0},"angles":{"x":-90.0,"y":0.0,"z":0.0}},{"classname":"light_spot","origin":{"x":1336.0,"y":1597.0,"z":-1223.0},"angles":{"x":90.0,"y":90.0,"z":0.0}},{"classname":"point_spotlight","origin":{"x":1336.0,"y":775.0,"z":-1218.99},"angles":{"x":-90.0,"y":0.0,"z":0.0}},{"classname":"light_spot","origin":{"x":1336.0,"y":775.0,"z":-1222.99},"angles":{"x":90.0,"y":90.0,"z":0.0}},{"classname":"point_spotlight","origin":{"x":1336.0,"y":-262.0,"z":-1217.0},"angles":{"x":-90.0,"y":0.0,"z":0.0}},{"classname":"light_spot","origin":{"x":1336.0,"y":-262.0,"z":-1221.0},"angles":{"x":90.0,"y":90.0,"z":0.0}},{"classname":"point_spotlight","origin":{"x":-280.0,"y":-262.0,"z":-1217.0},"angles":{"x":-90.0,"y":0.0,"z":0.0}},{"classname":"light_spot","origin":{"x":-280.0,"y":-262.0,"z":-1221.0},"angles":{"x":90.0,"y":90.0,"z":0.0}},{"classname":"point_spotlight","origin":{"x":-280.0,"y":775.0,"z":-1218.99},"angles":{"x":-90.0,"y":0.0,"z":0.0}},{"classname":"light_spot","origin":{"x":-280.0,"y":775.0,"z":-1222.99},"angles":{"x":90.0,"y":90.0,"z":0.0}},{"classname":"point_spotlight","origin":{"x":-280.0,"y":1597.0,"z":-1219.0},"angles":{"x":-90.0,"y":0.0,"z":0.0}},{"classname":"light_spot","origin":{"x":-280.0,"y":1597.0,"z":-1223.0},"angles":{"x":90.0,"y":90.0,"z":0.0}},{"classname":"point_spotlight","origin":{"x":-280.0,"y":-862.0,"z":-1219.0},"angles":{"x":-90.0,"y":0.0,"z":0.0}},{"classname":"light_spot","origin":{"x":-280.0,"y":-862.0,"z":-1223.0},"angles":{"x":90.0,"y":90.0,"z":0.0}},{"classname":"point_spotlight","origin":{"x":1336.0,"y":-862.0,"z":-1219.0},"angles":{"x":-90.0,"y":0.0,"z":0.0}},{"classname":"light_spot","origin":{"x":1336.0,"y":-862.0,"z":-1223.0},"angles":{"x":90.0,"y":90.0,"z":0.0}},{"classname":"point_spotlight","origin":{"x":-280.0,"y":246.0,"z":-3007.99},"angles":{"x":-90.0,"y":0.0,"z":0.0}},{"classname":"light_spot","origin":{"x":-280.0,"y":246.0,"z":-3011.99},"angles":{"x":90.0,"y":90.0,"z":0.0}},{"classname":"point_spotlight","origin":{"x":1336.0,"y":246.0,"z":-3007.99},"angles":{"x":-90.0,"y":0.0,"z":0.0}},{"classname":"light_spot","origin":{"x":1336.0,"y":246.0,"z":-3011.99},"angles":{"x":90.0,"y":90.0,"z":0.0}},{"classname":"point_spotlight","origin":{"x":-280.0,"y":-576.0,"z":-3007.99},"angles":{"x":-90.0,"y":0.0,"z":0.0}},{"classname":"light_spot","origin":{"x":-280.0,"y":-576.0,"z":-3012.0},"angles":{"x":90.0,"y":90.0,"z":0.0}},{"model":4,"clusters":[314,319,329,340,348,361,363,372,731,741,742,749,1032,1034,1037,1043,1045,1047,1049,1051,1056,1058,1067,1073,1078,1085,1102,1108,1113,1116,1119,1121,1124,1128,1132,1137,1140,1142,1146,1148,1159,1161,1175,1917,1921,1922,1926,1932,1934,1937],"classname":"func_brush","origin":{"x":528.0,"y":1068.0,"z":-3028.0}},{"classname":"light_spot","origin":{"x":1336.0,"y":-576.0,"z":-3012.0},"angles":{"x":90.0,"y":90.0,"z":0.0}},{"classname":"point_spotlight","origin":{"x":1336.0,"y":-576.0,"z":-3007.99},"angles":{"x":-90.0,"y":0.0,"z":0.0}},{"classname":"point_spotlight","origin":{"x":-280.0,"y":-1398.0,"z":-3007.99},"angles":{"x":-90.0,"y":0.0,"z":0.0}},{"classname":"light_spot","origin":{"x":-280.0,"y":-1398.0,"z":-3011.99},"angles":{"x":90.0,"y":90.0,"z":0.0}},{"classname":"point_spotlight","origin":{"x":-280.0,"y":-2220.0,"z":-3007.99},"angles":{"x":-90.0,"y":0.0,"z":0.0}},{"classname":"light_spot","origin":{"x":-280.0,"y":-2220.0,"z":-3011.99},"angles":{"x":90.0,"y":90.0,"z":0.0}},{"classname":"light_spot","origin":{"x":1336.0,"y":-2220.0,"z":-3011.99},"angles":{"x":90.0,"y":90.0,"z":0.0}},{"classname":"point_spotlight","origin":{"x":1336.0,"y":-2220.0,"z":-3007.99},"angles":{"x":-90.0,"y":0.0,"z":0.0}},{"classname":"point_spotlight","origin":{"x":1336.0,"y":-1398.0,"z":-3007.99},"angles":{"x":-90.0,"y":0.0,"z":0.0}},{"classname":"light_spot","origin":{"x":1336.0,"y":-1398.0,"z":-3011.99},"angles":{"x":90.0,"y":90.0,"z":0.0}},{"classname":"point_spotlight","origin":{"x":-280.0,"y":1068.0,"z":-3007.99},"angles":{"x":-90.0,"y":0.0,"z":0.0}},{"classname":"light_spot","origin":{"x":-280.0,"y":1068.0,"z":-3011.99},"angles":{"x":90.0,"y":90.0,"z":0.0}},{"classname":"point_spotlight","origin":{"x":-280.0,"y":1890.0,"z":-3007.99},"angles":{"x":-90.0,"y":0.0,"z":0.0}},{"classname":"light_spot","origin":{"x":-280.0,"y":1890.0,"z":-3011.99},"angles":{"x":90.0,"y":90.0,"z":0.0}},{"classname":"point_spotlight","origin":{"x":1336.0,"y":1890.0,"z":-3007.99},"angles":{"x":-90.0,"y":0.0,"z":0.0}},{"classname":"light_spot","origin":{"x":1336.0,"y":1890.0,"z":-3011.99},"angles":{"x":90.0,"y":90.0,"z":0.0}},{"classname":"light_spot","origin":{"x":1336.0,"y":1068.0,"z":-3011.99},"angles":{"x":90.0,"y":90.0,"z":0.0}},{"classname":"point_spotlight","origin":{"x":1336.0,"y":1068.0,"z":-3007.99},"angles":{"x":-90.0,"y":0.0,"z":0.0}},{"classname":"point_spotlight","origin":{"x":-280.0,"y":2712.0,"z":-3007.99},"angles":{"x":-90.0,"y":0.0,"z":0.0}},{"classname":"light_spot","origin":{"x":-280.0,"y":2712.0,"z":-3012.0},"angles":{"x":90.0,"y":90.0,"z":0.0}},{"classname":"light_spot","origin":{"x":1336.0,"y":2712.0,"z":-3012.0},"angles":{"x":90.0,"y":90.0,"z":0.0}},{"classname":"point_spotlight","origin":{"x":1336.0,"y":2712.0,"z":-3007.99},"angles":{"x":-90.0,"y":0.0,"z":0.0}},{"classname":"point_spotlight","origin":{"x":1336.0,"y":3534.0,"z":-3007.99},"angles":{"x":-90.0,"y":0.0,"z":0.0}},{"classname":"light_spot","origin":{"x":1336.0,"y":3534.0,"z":-3011.99},"angles":{"x":90.0,"y":90.0,"z":0.0}},{"classname":"point_spotlight","origin":{"x":1336.0,"y":4356.0,"z":-3008.0},"angles":{"x":-90.0,"y":0.0,"z":0.0}},{"classname":"light_spot","origin":{"x":1336.0,"y":4356.0,"z":-3012.0},"angles":{"x":90.0,"y":90.0,"z":0.0}},{"classname":"point_spotlight","origin":{"x":-280.0,"y":4356.0,"z":-3008.0},"angles":{"x":-90.0,"y":0.0,"z":0.0}},{"classname":"light_spot","origin":{"x":-280.0,"y":4356.0,"z":-3012.0},"angles":{"x":90.0,"y":90.0,"z":0.0}},{"classname":"point_spotlight","origin":{"x":-280.0,"y":3534.0,"z":-3007.99},"angles":{"x":-90.0,"y":0.0,"z":0.0}},{"classname":"light_spot","origin":{"x":-280.0,"y":3534.0,"z":-3011.99},"angles":{"x":90.0,"y":90.0,"z":0.0}},{"classname":"water_lod_control","origin":{"x":9488.0,"y":4913.0,"z":2782.26}},{"targetname":"desty_stage4","classname":"info_teleport_destination","origin":{"x":9488.0,"y":4974.0,"z":2969.26},"angles":{"x":0.0,"y":270.0,"z":0.0}},{"targetname":"dmgfilter_5","classname":"filter_damage_type","origin":{"x":9927.0,"y":5064.0,"z":2767.15}},{"classname":"light","origin":{"x":9488.0,"y":4913.0,"z":2914.26}},{"classname":"trigger_teleport","origin":{"x":9488.0,"y":4975.0,"z":3012.5}},{"classname":"point_spotlight","origin":{"x":8592.0,"y":4049.0,"z":1016.0},"angles":{"x":-90.0,"y":0.0,"z":0.0}},{"classname":"light_spot","origin":{"x":8592.0,"y":4049.0,"z":1012.0},"angles":{"x":90.0,"y":90.0,"z":0.0}},{"classname":"point_spotlight","origin":{"x":8592.0,"y":3391.0,"z":1016.0},"angles":{"x":-90.0,"y":0.0,"z":0.0}},{"classname":"light_spot","origin":{"x":8592.0,"y":3391.0,"z":1012.0},"angles":{"x":90.0,"y":90.0,"z":0.0}},{"classname":"point_spotlight","origin":{"x":8592.0,"y":2735.0,"z":1016.0},"angles":{"x":-90.0,"y":0.0,"z":0.0}},{"classname":"light_spot","origin":{"x":8592.0,"y":2735.0,"z":1012.0},"angles":{"x":90.0,"y":90.0,"z":0.0}},{"classname":"point_spotlight","origin":{"x":8592.0,"y":2078.44,"z":1015.59},"angles":{"x":-90.0,"y":0.0,"z":0.0}},{"classname":"light_spot","origin":{"x":8592.0,"y":2078.44,"z":1011.59},"angles":{"x":90.0,"y":90.0,"z":0.0}},{"classname":"point_spotlight","origin":{"x":10384.0,"y":4049.0,"z":1016.0},"angles":{"x":-90.0,"y":0.0,"z":0.0}},{"classname":"light_spot","origin":{"x":10384.0,"y":4049.0,"z":1012.0},"angles":{"x":90.0,"y":90.0,"z":0.0}},{"classname":"point_spotlight","origin":{"x":10384.0,"y":3391.0,"z":1016.0},"angles":{"x":-90.0,"y":0.0,"z":0.0}},{"classname":"light_spot","origin":{"x":10384.0,"y":3391.0,"z":1012.0},"angles":{"x":90.0,"y":90.0,"z":0.0}},{"classname":"point_spotlight","origin":{"x":10384.0,"y":2735.0,"z":1016.0},"angles":{"x":-90.0,"y":0.0,"z":0.0}},{"classname":"light_spot","origin":{"x":10384.0,"y":2735.0,"z":1012.0},"angles":{"x":90.0,"y":90.0,"z":0.0}},{"classname":"point_spotlight","origin":{"x":10384.0,"y":2078.44,"z":1015.59},"angles":{"x":-90.0,"y":0.0,"z":0.0}},{"classname":"light_spot","origin":{"x":10384.0,"y":2078.44,"z":1011.59},"angles":{"x":90.0,"y":90.0,"z":0.0}},{"classname":"point_spotlight","origin":{"x":8592.0,"y":1424.44,"z":1015.59},"angles":{"x":-90.0,"y":0.0,"z":0.0}},{"classname":"light_spot","origin":{"x":8592.0,"y":1424.44,"z":1011.59},"angles":{"x":90.0,"y":90.0,"z":0.0}},{"classname":"point_spotlight","origin":{"x":10384.0,"y":1424.44,"z":1015.59},"angles":{"x":-90.0,"y":0.0,"z":0.0}},{"classname":"light_spot","origin":{"x":10384.0,"y":1424.44,"z":1011.59},"angles":{"x":90.0,"y":90.0,"z":0.0}},{"classname":"point_spotlight","origin":{"x":8816.0,"y":4913.0,"z":2392.0},"angles":{"x":-90.0,"y":0.0,"z":0.0}},{"classname":"light_spot","origin":{"x":8816.0,"y":4913.0,"z":2388.0},"angles":{"x":90.0,"y":90.0,"z":0.0}},{"classname":"point_spotlight","origin":{"x":10160.0,"y":4913.0,"z":2392.0},"angles":{"x":-90.0,"y":0.0,"z":0.0}},{"classname":"light_spot","origin":{"x":10160.0,"y":4913.0,"z":2388.0},"angles":{"x":90.0,"y":90.0,"z":0.0}},{"classname":"point_spotlight","origin":{"x":8592.0,"y":1521.0,"z":-8.0},"angles":{"x":-90.0,"y":0.0,"z":0.0}},{"classname":"light_spot","origin":{"x":8592.0,"y":1521.0,"z":-12.0},"angles":{"x":90.0,"y":90.0,"z":0.0}},{"classname":"point_spotlight","origin":{"x":8592.0,"y":863.0,"z":-8.0},"angles":{"x":-90.0,"y":0.0,"z":0.0}},{"classname":"light_spot","origin":{"x":8592.0,"y":863.0,"z":-12.0},"angles":{"x":90.0,"y":90.0,"z":0.0}},{"classname":"point_spotlight","origin":{"x":8592.0,"y":-449.56,"z":-8.4099},"angles":{"x":-90.0,"y":0.0,"z":0.0}},{"classname":"light_spot","origin":{"x":8592.0,"y":-449.56,"z":-12.4099},"angles":{"x":90.0,"y":90.0,"z":0.0}},{"classname":"point_spotlight","origin":{"x":8592.0,"y":207.0,"z":-8.0},"angles":{"x":-90.0,"y":0.0,"z":0.0}},{"classname":"light_spot","origin":{"x":8592.0,"y":207.0,"z":-12.0},"angles":{"x":90.0,"y":90.0,"z":0.0}},{"classname":"point_spotlight","origin":{"x":8592.0,"y":-1103.56,"z":-8.4099},"angles":{"x":-90.0,"y":0.0,"z":0.0}},{"classname":"light_spot","origin":{"x":8592.0,"y":-1103.56,"z":-12.4099},"angles":{"x":90.0,"y":90.0,"z":0.0}},{"classname":"point_spotlight","origin":{"x":10384.0,"y":1521.0,"z":-8.0},"angles":{"x":-90.0,"y":0.0,"z":0.0}},{"classname":"light_spot","origin":{"x":10384.0,"y":1521.0,"z":-12.0},"angles":{"x":90.0,"y":90.0,"z":0.0}},{"classname":"point_spotlight","origin":{"x":10384.0,"y":863.0,"z":-8.0},"angles":{"x":-90.0,"y":0.0,"z":0.0}},{"classname":"light_spot","origin":{"x":10384.0,"y":863.0,"z":-12.0},"angles":{"x":90.0,"y":90.0,"z":0.0}},{"classname":"point_spotlight","origin":{"x":10384.0,"y":207.0,"z":-8.0},"angles":{"x":-90.0,"y":0.0,"z":0.0}},{"classname":"light_spot","origin":{"x":10384.0,"y":207.0,"z":-12.0},"angles":{"x":90.0,"y":90.0,"z":0.0}},{"classname":"point_spotlight","origin":{"x":10384.0,"y":-449.56,"z":-8.4099},"angles":{"x":-90.0,"y":0.0,"z":0.0}},{"classname":"light_spot","origin":{"x":10384.0,"y":-449.56,"z":-12.4099},"angles":{"x":90.0,"y":90.0,"z":0.0}},{"classname":"point_spotlight","origin":{"x":10384.0,"y":-1103.56,"z":-8.4099},"angles":{"x":-90.0,"y":0.0,"z":0.0}},{"classname":"light_spot","origin":{"x":10384.0,"y":-1103.56,"z":-12.4099},"angles":{"x":90.0,"y":90.0,"z":0.0}},{"classname":"point_spotlight","origin":{"x":8784.0,"y":1489.0,"z":-1992.0},"angles":{"x":-90.0,"y":0.0,"z":0.0}},{"classname":"light_spot","origin":{"x":8784.0,"y":1489.0,"z":-1996.0},"angles":{"x":90.0,"y":90.0,"z":0.0}},{"classname":"point_spotlight","origin":{"x":8784.0,"y":831.0,"z":-1992.0},"angles":{"x":-90.0,"y":0.0,"z":0.0}},{"classname":"light_spot","origin":{"x":8784.0,"y":831.0,"z":-1996.0},"angles":{"x":90.0,"y":90.0,"z":0.0}},{"classname":"point_spotlight","origin":{"x":8784.0,"y":-481.56,"z":-1992.41},"angles":{"x":-90.0,"y":0.0,"z":0.0}},{"classname":"light_spot","origin":{"x":8784.0,"y":-481.56,"z":-1996.41},"angles":{"x":90.0,"y":90.0,"z":0.0}},{"classname":"point_spotlight","origin":{"x":8784.0,"y":175.0,"z":-1992.0},"angles":{"x":-90.0,"y":0.0,"z":0.0}},{"classname":"light_spot","origin":{"x":8784.0,"y":175.0,"z":-1996.0},"angles":{"x":90.0,"y":90.0,"z":0.0}},{"model":6,"clusters":[168,170,171,184,186,198,207,209,212,223,233,249,251,252,282,404,405,406,407,414,416,417,418,425,427,428,433,440,444,448,455,470,471,472,473,486],"classname":"func_brush","origin":{"x":9488.0,"y":177.0,"z":-2012.0}},{"classname":"point_spotlight","origin":{"x":8784.0,"y":-1135.56,"z":-1992.41},"angles":{"x":-90.0,"y":0.0,"z":0.0}},{"classname":"light_spot","origin":{"x":8784.0,"y":-1135.56,"z":-1996.41},"angles":{"x":90.0,"y":90.0,"z":0.0}},{"classname":"point_spotlight","origin":{"x":10192.0,"y":1489.0,"z":-1992.0},"angles":{"x":-90.0,"y":0.0,"z":0.0}},{"classname":"light_spot","origin":{"x":10192.0,"y":1489.0,"z":-1996.0},"angles":{"x":90.0,"y":90.0,"z":0.0}},{"classname":"point_spotlight","origin":{"x":10192.0,"y":831.0,"z":-1992.0},"angles":{"x":-90.0,"y":0.0,"z":0.0}},{"classname":"light_spot","origin":{"x":10192.0,"y":831.0,"z":-1996.0},"angles":{"x":90.0,"y":90.0,"z":0.0}},{"classname":"point_spotlight","origin":{"x":10192.0,"y":175.0,"z":-1992.0},"angles":{"x":-90.0,"y":0.0,"z":0.0}},{"classname":"light_spot","origin":{"x":10192.0,"y":175.0,"z":-1996.0},"angles":{"x":90.0,"y":90.0,"z":0.0}},{"classname":"point_spotlight","origin":{"x":10192.0,"y":-481.56,"z":-1992.41},"angles":{"x":-90.0,"y":0.0,"z":0.0}},{"classname":"light_spot","origin":{"x":10192.0,"y":-481.56,"z":-1996.41},"angles":{"x":90.0,"y":90.0,"z":0.0}},{"classname":"point_spotlight","origin":{"x":10192.0,"y":-1135.56,"z":-1992.41},"angles":{"x":-90.0,"y":0.0,"z":0.0}},{"classname":"light_spot","origin":{"x":10192.0,"y":-1135.56,"z":-1996.41},"angles":{"x":90.0,"y":90.0,"z":0.0}},{"classname":"point_spotlight","origin":{"x":10256.0,"y":1735.0,"z":-3064.0},"angles":{"x":-90.0,"y":0.0,"z":0.0}},{"classname":"light_spot","origin":{"x":10256.0,"y":1735.0,"z":-3068.0},"angles":{"x":90.0,"y":90.0,"z":0.0}},{"classname":"point_spotlight","origin":{"x":10256.0,"y":1077.0,"z":-3064.0},"angles":{"x":-90.0,"y":0.0,"z":0.0}},{"classname":"light_spot","origin":{"x":10256.0,"y":1077.0,"z":-3068.0},"angles":{"x":90.0,"y":90.0,"z":0.0}},{"classname":"point_spotlight","origin":{"x":10256.0,"y":421.0,"z":-3064.0},"angles":{"x":-90.0,"y":0.0,"z":0.0}},{"classname":"light_spot","origin":{"x":10256.0,"y":421.0,"z":-3068.0},"angles":{"x":90.0,"y":90.0,"z":0.0}},{"classname":"point_spotlight","origin":{"x":10256.0,"y":-235.56,"z":-3064.41},"angles":{"x":-90.0,"y":0.0,"z":0.0}},{"classname":"light_spot","origin":{"x":10256.0,"y":-235.56,"z":-3068.41},"angles":{"x":90.0,"y":90.0,"z":0.0}},{"classname":"point_spotlight","origin":{"x":10256.0,"y":-889.56,"z":-3064.41},"angles":{"x":-90.0,"y":0.0,"z":0.0}},{"classname":"light_spot","origin":{"x":10256.0,"y":-889.56,"z":-3068.41},"angles":{"x":90.0,"y":90.0,"z":0.0}},{"classname":"point_spotlight","origin":{"x":8720.0,"y":1735.0,"z":-3064.0},"angles":{"x":-90.0,"y":0.0,"z":0.0}},{"classname":"light_spot","origin":{"x":8720.0,"y":1735.0,"z":-3068.0},"angles":{"x":90.0,"y":90.0,"z":0.0}},{"classname":"point_spotlight","origin":{"x":8720.0,"y":1077.0,"z":-3064.0},"angles":{"x":-90.0,"y":0.0,"z":0.0}},{"classname":"light_spot","origin":{"x":8720.0,"y":1077.0,"z":-3068.0},"angles":{"x":90.0,"y":90.0,"z":0.0}},{"classname":"point_spotlight","origin":{"x":8720.0,"y":421.0,"z":-3064.0},"angles":{"x":-90.0,"y":0.0,"z":0.0}},{"classname":"light_spot","origin":{"x":8720.0,"y":421.0,"z":-3068.0},"angles":{"x":90.0,"y":90.0,"z":0.0}},{"classname":"point_spotlight","origin":{"x":8720.0,"y":-235.56,"z":-3064.41},"angles":{"x":-90.0,"y":0.0,"z":0.0}},{"classname":"light_spot","origin":{"x":8720.0,"y":-235.56,"z":-3068.41},"angles":{"x":90.0,"y":90.0,"z":0.0}},{"classname":"point_spotlight","origin":{"x":8720.0,"y":-889.56,"z":-3064.41},"angles":{"x":-90.0,"y":0.0,"z":0.0}},{"classname":"light_spot","origin":{"x":8720.0,"y":-889.56,"z":-3068.41},"angles":{"x":90.0,"y":90.0,"z":0.0}},{"classname":"point_spotlight","origin":{"x":10256.0,"y":2393.0,"z":-3064.0},"angles":{"x":-90.0,"y":0.0,"z":0.0}},{"classname":"light_spot","origin":{"x":10256.0,"y":2393.0,"z":-3068.0},"angles":{"x":90.0,"y":90.0,"z":0.0}},{"classname":"point_spotlight","origin":{"x":8720.0,"y":2393.0,"z":-3064.0},"angles":{"x":-90.0,"y":0.0,"z":0.0}},{"classname":"light_spot","origin":{"x":8720.0,"y":2393.0,"z":-3068.0},"angles":{"x":90.0,"y":90.0,"z":0.0}},{"classname":"point_spotlight","origin":{"x":9488.0,"y":16.4399,"z":1559.59},"angles":{"x":-90.0,"y":0.0,"z":0.0}},{"classname":"light_spot","origin":{"x":9488.0,"y":16.4399,"z":1555.59},"angles":{"x":90.0,"y":90.0,"z":0.0}},{"classname":"point_spotlight","origin":{"x":9488.0,"y":-637.56,"z":1559.59},"angles":{"x":-90.0,"y":0.0,"z":0.0}},{"classname":"light_spot","origin":{"x":9488.0,"y":-637.56,"z":1555.59},"angles":{"x":90.0,"y":90.0,"z":0.0}},{"classname":"point_spotlight","origin":{"x":9488.0,"y":-1293.56,"z":1559.59},"angles":{"x":-90.0,"y":0.0,"z":0.0}},{"classname":"light_spot","origin":{"x":9488.0,"y":-1293.56,"z":1555.59},"angles":{"x":90.0,"y":90.0,"z":0.0}},{"classname":"point_spotlight","origin":{"x":8552.0,"y":880.44,"z":1871.59},"angles":{"x":-90.0,"y":0.0,"z":0.0}},{"classname":"light_spot","origin":{"x":8552.0,"y":880.44,"z":1867.59},"angles":{"x":90.0,"y":90.0,"z":0.0}},{"classname":"point_spotlight","origin":{"x":10432.0,"y":880.44,"z":1871.59},"angles":{"x":-90.0,"y":0.0,"z":0.0}},{"classname":"light_spot","origin":{"x":10432.0,"y":880.44,"z":1867.59},"angles":{"x":90.0,"y":90.0,"z":0.0}},{"classname":"light","origin":{"x":8664.0,"y":1577.0,"z":-2480.0}},{"classname":"light","origin":{"x":8664.0,"y":2233.0,"z":-2480.0}},{"classname":"light","origin":{"x":8664.0,"y":-391.0,"z":-2480.0}},{"classname":"light","origin":{"x":8664.0,"y":265.0,"z":-2480.0}},{"classname":"light","origin":{"x":8664.0,"y":921.0,"z":-2480.0}},{"classname":"light","origin":{"x":8664.0,"y":-1047.0,"z":-2480.0}},{"classname":"light","origin":{"x":10360.0,"y":1577.0,"z":-2488.0}},{"classname":"light","origin":{"x":10360.0,"y":2233.0,"z":-2488.0}},{"classname":"light","origin":{"x":10360.0,"y":-391.0,"z":-2488.0}},{"classname":"light","origin":{"x":10360.0,"y":265.0,"z":-2488.0}},{"classname":"light","origin":{"x":10360.0,"y":921.0,"z":-2488.0}},{"classname":"light","origin":{"x":10360.0,"y":-1047.0,"z":-2488.0}},{"classname":"light","origin":{"x":10208.0,"y":1577.0,"z":-1616.0}},{"classname":"light","origin":{"x":10208.0,"y":2121.0,"z":-936.0}},{"classname":"light","origin":{"x":10208.0,"y":-391.0,"z":-1616.0}},{"classname":"light","origin":{"x":10208.0,"y":265.0,"z":-1616.0}},{"classname":"light","origin":{"x":10208.0,"y":921.0,"z":-1616.0}},{"classname":"light","origin":{"x":10208.0,"y":-1047.0,"z":-1616.0}},{"classname":"light","origin":{"x":10208.0,"y":2809.0,"z":-384.0}},{"classname":"light","origin":{"x":8776.0,"y":2121.0,"z":-928.0}},{"classname":"light","origin":{"x":8776.0,"y":1577.0,"z":-1608.0}},{"classname":"light","origin":{"x":8776.0,"y":-391.0,"z":-1608.0}},{"classname":"light","origin":{"x":8776.0,"y":265.0,"z":-1608.0}},{"classname":"light","origin":{"x":8776.0,"y":921.0,"z":-1608.0}},{"classname":"light","origin":{"x":8776.0,"y":-1047.0,"z":-1608.0}},{"classname":"light","origin":{"x":8736.0,"y":2070.33,"z":584.0}},{"classname":"light","origin":{"x":8736.0,"y":-553.67,"z":584.0}},{"classname":"light","origin":{"x":8736.0,"y":321.0,"z":584.0}},{"classname":"light","origin":{"x":8736.0,"y":1195.67,"z":584.0}},{"classname":"light","origin":{"x":8736.0,"y":-1428.33,"z":584.0}},{"classname":"light","origin":{"x":10264.0,"y":2070.33,"z":584.0}},{"classname":"light","origin":{"x":10264.0,"y":-553.67,"z":584.0}},{"classname":"light","origin":{"x":10264.0,"y":321.0,"z":584.0}},{"classname":"light","origin":{"x":10264.0,"y":1195.67,"z":584.0}},{"classname":"light","origin":{"x":10264.0,"y":-1428.33,"z":584.0}},{"classname":"light","origin":{"x":10264.0,"y":-521.67,"z":2336.0}},{"classname":"light","origin":{"x":10264.0,"y":353.0,"z":2336.0}},{"classname":"light","origin":{"x":10264.0,"y":1227.67,"z":2336.0}},{"classname":"light","origin":{"x":10264.0,"y":-1396.33,"z":2336.0}},{"classname":"light","origin":{"x":8704.0,"y":-521.67,"z":2352.0}},{"classname":"light","origin":{"x":8704.0,"y":353.0,"z":2352.0}},{"classname":"light","origin":{"x":8704.0,"y":1227.67,"z":2352.0}},{"classname":"light","origin":{"x":8704.0,"y":-1396.33,"z":2352.0}},{"classname":"light","origin":{"x":10384.0,"y":4313.0,"z":2120.0}},{"classname":"light","origin":{"x":10384.0,"y":1726.33,"z":1416.0}},{"classname":"light","origin":{"x":10384.0,"y":2785.0,"z":1672.0}},{"classname":"light","origin":{"x":10384.0,"y":3777.0,"z":1768.0}},{"classname":"light","origin":{"x":10384.0,"y":851.67,"z":1416.0}},{"classname":"light","origin":{"x":8584.0,"y":4313.0,"z":2120.0}},{"classname":"light","origin":{"x":8584.0,"y":1726.33,"z":1416.0}},{"classname":"light","origin":{"x":8584.0,"y":2785.0,"z":1672.0}},{"classname":"light","origin":{"x":8584.0,"y":3777.0,"z":1768.0}},{"classname":"light","origin":{"x":8584.0,"y":851.67,"z":1416.0}},{"classname":"logic_auto","origin":{"x":-10641.0,"y":7408.0,"z":416.616}},{"targetname":"dissolver_spawn","classname":"env_entity_dissolver","origin":{"x":-10647.0,"y":7398.0,"z":416.616}},{"targetname":"command","classname":"point_servercommand","origin":{"x":-10641.0,"y":7424.0,"z":416.616}},{"classname":"game_player_equip","origin":{"x":-10641.0,"y":7440.0,"z":416.616}},{"classname":"trigger_teleport","origin":{"x":8084.0,"y":753.0,"z":-2349.0}},{"classname":"trigger_teleport","origin":{"x":10892.0,"y":753.0,"z":-2348.99}},{"classname":"info_player_terrorist","origin":{"x":-10374.7,"y":7385.8,"z":186.619},"angles":{"x":0.0,"y":0.0,"z":0.0}},{"classname":"info_player_terrorist","origin":{"x":-10680.3,"y":7385.3,"z":186.619},"angles":{"x":0.0,"y":0.0,"z":0.0}},{"classname":"info_player_terrorist","origin":{"x":-10452.7,"y":7385.8,"z":186.619},"angles":{"x":0.0,"y":0.0,"z":0.0}},{"classname":"info_player_terrorist","origin":{"x":-10528.1,"y":7385.6,"z":186.619},"angles":{"x":0.0,"y":0.0,"z":0.0}},{"classname":"info_player_terrorist","origin":{"x":-10604.6,"y":7385.6,"z":186.619},"angles":{"x":0.0,"y":0.0,"z":0.0}},{"classname":"info_player_terrorist","origin":{"x":-10760.5,"y":7385.2,"z":186.619},"angles":{"x":0.0,"y":0.0,"z":0.0}},{"classname":"info_player_terrorist","origin":{"x":-10374.7,"y":7261.4,"z":186.619},"angles":{"x":0.0,"y":0.0,"z":0.0}},{"classname":"info_player_terrorist","origin":{"x":-10760.5,"y":7260.8,"z":186.619},"angles":{"x":0.0,"y":0.0,"z":0.0}},{"classname":"info_player_terrorist","origin":{"x":-10452.7,"y":7261.4,"z":186.619},"angles":{"x":0.0,"y":0.0,"z":0.0}},{"classname":"info_player_terrorist","origin":{"x":-10528.1,"y":7261.2,"z":186.619},"angles":{"x":0.0,"y":0.0,"z":0.0}},{"classname":"info_player_terrorist","origin":{"x":-10604.6,"y":7261.2,"z":186.619},"angles":{"x":0.0,"y":0.0,"z":0.0}},{"classname":"info_player_terrorist","origin":{"x":-10680.3,"y":7260.9,"z":186.619},"angles":{"x":0.0,"y":0.0,"z":0.0}},{"classname":"info_player_terrorist","origin":{"x":-10373.7,"y":7148.8,"z":186.619},"angles":{"x":0.0,"y":0.0,"z":0.0}},{"classname":"info_player_terrorist","origin":{"x":-10451.7,"y":7148.8,"z":186.619},"angles":{"x":0.0,"y":0.0,"z":0.0}},{"classname":"info_player_terrorist","origin":{"x":-10527.4,"y":7148.5,"z":186.619},"angles":{"x":0.0,"y":0.0,"z":0.0}},{"classname":"info_player_terrorist","origin":{"x":-10603.9,"y":7148.5,"z":186.619},"angles":{"x":0.0,"y":0.0,"z":0.0}},{"classname":"info_player_terrorist","origin":{"x":-10679.3,"y":7148.3,"z":186.619},"angles":{"x":0.0,"y":0.0,"z":0.0}},{"classname":"info_player_terrorist","origin":{"x":-10759.5,"y":7148.2,"z":186.619},"angles":{"x":0.0,"y":0.0,"z":0.0}},{"classname":"info_player_counterterrorist","origin":{"x":-10385.4,"y":7806.3,"z":186.542},"angles":{"x":0.0,"y":0.0,"z":0.0}},{"classname":"info_player_counterterrorist","origin":{"x":-10756.8,"y":7801.7,"z":186.619},"angles":{"x":0.0,"y":0.0,"z":0.0}},{"classname":"info_player_counterterrorist","origin":{"x":-10679.3,"y":7801.4,"z":186.619},"angles":{"x":0.0,"y":0.0,"z":0.0}},{"classname":"info_player_counterterrorist","origin":{"x":-10603.9,"y":7801.7,"z":186.619},"angles":{"x":0.0,"y":0.0,"z":0.0}},{"classname":"info_player_counterterrorist","origin":{"x":-10527.4,"y":7801.7,"z":186.619},"angles":{"x":0.0,"y":0.0,"z":0.0}},{"classname":"info_player_counterterrorist","origin":{"x":-10451.7,"y":7801.8,"z":186.619},"angles":{"x":0.0,"y":0.0,"z":0.0}},{"classname":"info_player_counterterrorist","origin":{"x":-10386.4,"y":8043.9,"z":186.542},"angles":{"x":0.0,"y":0.0,"z":0.0}},{"classname":"info_player_counterterrorist","origin":{"x":-10757.6,"y":8039.3,"z":186.619},"angles":{"x":0.0,"y":0.0,"z":0.0}},{"classname":"info_player_counterterrorist","origin":{"x":-10680.3,"y":8039.2,"z":186.619},"angles":{"x":0.0,"y":0.0,"z":0.0}},{"classname":"info_player_counterterrorist","origin":{"x":-10604.6,"y":8039.3,"z":186.619},"angles":{"x":0.0,"y":0.0,"z":0.0}},{"classname":"info_player_counterterrorist","origin":{"x":-10528.1,"y":8039.3,"z":186.619},"angles":{"x":0.0,"y":0.0,"z":0.0}},{"classname":"info_player_counterterrorist","origin":{"x":-10452.7,"y":8039.5,"z":186.619},"angles":{"x":0.0,"y":0.0,"z":0.0}},{"classname":"info_player_terrorist","origin":{"x":-10374.7,"y":7473.8,"z":186.619},"angles":{"x":0.0,"y":0.0,"z":0.0}},{"classname":"info_player_terrorist","origin":{"x":-10680.3,"y":7473.3,"z":186.619},"angles":{"x":0.0,"y":0.0,"z":0.0}},{"classname":"info_player_terrorist","origin":{"x":-10452.7,"y":7473.8,"z":186.619},"angles":{"x":0.0,"y":0.0,"z":0.0}},{"classname":"info_player_terrorist","origin":{"x":-10528.1,"y":7473.6,"z":186.619},"angles":{"x":0.0,"y":0.0,"z":0.0}},{"classname":"info_player_terrorist","origin":{"x":-10604.6,"y":7473.6,"z":186.619},"angles":{"x":0.0,"y":0.0,"z":0.0}},{"classname":"info_player_terrorist","origin":{"x":-10760.5,"y":7473.2,"z":186.619},"angles":{"x":0.0,"y":0.0,"z":0.0}},{"classname":"info_player_counterterrorist","origin":{"x":-10385.4,"y":7710.3,"z":186.542},"angles":{"x":0.0,"y":0.0,"z":0.0}},{"classname":"info_player_counterterrorist","origin":{"x":-10756.8,"y":7705.7,"z":186.619},"angles":{"x":0.0,"y":0.0,"z":0.0}},{"classname":"info_player_counterterrorist","origin":{"x":-10679.3,"y":7705.4,"z":186.619},"angles":{"x":0.0,"y":0.0,"z":0.0}},{"classname":"info_player_counterterrorist","origin":{"x":-10603.9,"y":7705.7,"z":186.619},"angles":{"x":0.0,"y":0.0,"z":0.0}},{"classname":"info_player_counterterrorist","origin":{"x":-10527.4,"y":7705.7,"z":186.619},"angles":{"x":0.0,"y":0.0,"z":0.0}},{"classname":"info_player_counterterrorist","origin":{"x":-10451.7,"y":7705.8,"z":186.619},"angles":{"x":0.0,"y":0.0,"z":0.0}},{"targetname":"dmgfilter_spawn","classname":"filter_damage_type","origin":{"x":-10641.0,"y":7456.0,"z":417.0}},{"classname":"light","origin":{"x":-10621.5,"y":7611.0,"z":108.5}},{"classname":"light","origin":{"x":-10117.5,"y":7611.0,"z":340.5}},{"classname":"light","origin":{"x":-9653.5,"y":7611.0,"z":340.5}},{"classname":"light","origin":{"x":-9173.5,"y":7611.0,"z":340.5}},{"classname":"light","origin":{"x":-8701.5,"y":7611.0,"z":108.5}},{"classname":"trigger_once","origin":{"x":-9517.5,"y":7611.0,"z":60.5}},{"targetname":"spawn_door2","classname":"func_rot_button","origin":{"x":-8227.5,"y":7807.0,"z":28.5},"angles":{"x":0.0,"y":0.0,"z":0.0}},{"targetname":"spawn_door1","classname":"func_rot_button","origin":{"x":-8227.5,"y":7423.0,"z":28.5},"angles":{"x":0.0,"y":0.0,"z":0.0}},{"classname":"water_lod_control","origin":{"x":-9590.8,"y":7584.0,"z":-160.5}},{"classname":"light","origin":{"x":-8109.5,"y":7611.0,"z":60.5}},{"classname":"trigger_teleport","origin":{"x":-7983.0,"y":7615.0,"z":44.5}},{"classname":"trigger_multiple","origin":{"x":-9396.0,"y":7606.0,"z":-37.0}},{"classname":"water_lod_control","origin":{"x":-9360.0,"y":5250.6,"z":1167.26}},{"targetname":"desty_stage1","classname":"info_teleport_destination","origin":{"x":-9360.0,"y":5311.6,"z":1354.26},"angles":{"x":0.0,"y":270.0,"z":0.0}},{"targetname":"dmgfilter_1","classname":"filter_damage_type","origin":{"x":-8921.0,"y":5401.6,"z":1152.15}},{"classname":"light","origin":{"x":-9360.0,"y":5250.6,"z":1299.26}},{"classname":"trigger_teleport","origin":{"x":-9360.0,"y":5310.5,"z":1401.0}},{"classname":"point_spotlight","origin":{"x":-8552.0,"y":4754.6,"z":-119.0},"angles":{"x":-90.0,"y":0.0,"z":0.0}},{"classname":"light_spot","origin":{"x":-8552.0,"y":4754.6,"z":-123.0},"angles":{"x":90.0,"y":90.0,"z":0.0}},{"classname":"point_spotlight","origin":{"x":-10168.0,"y":4754.6,"z":-119.0},"angles":{"x":-90.0,"y":0.0,"z":0.0}},{"classname":"light_spot","origin":{"x":-10168.0,"y":4754.6,"z":-123.0},"angles":{"x":90.0,"y":90.0,"z":0.0}},{"classname":"point_spotlight","origin":{"x":-8552.0,"y":3770.57,"z":-119.0},"angles":{"x":-90.0,"y":0.0,"z":0.0}},{"classname":"light_spot","origin":{"x":-8552.0,"y":3770.57,"z":-123.0},"angles":{"x":90.0,"y":90.0,"z":0.0}},{"classname":"point_spotlight","origin":{"x":-8552.0,"y":2786.57,"z":-119.0},"angles":{"x":-90.0,"y":0.0,"z":0.0}},{"classname":"light_spot","origin":{"x":-8552.0,"y":2786.57,"z":-123.0},"angles":{"x":90.0,"y":90.0,"z":0.0}},{"classname":"point_spotlight","origin":{"x":-10168.0,"y":2786.57,"z":-119.0},"angles":{"x":-90.0,"y":0.0,"z":0.0}},{"classname":"light_spot","origin":{"x":-10168.0,"y":2786.57,"z":-123.0},"angles":{"x":90.0,"y":90.0,"z":0.0}},{"classname":"point_spotlight","origin":{"x":-10168.0,"y":3770.57,"z":-119.0},"angles":{"x":-90.0,"y":0.0,"z":0.0}},{"classname":"light_spot","origin":{"x":-10168.0,"y":3770.57,"z":-123.0},"angles":{"x":90.0,"y":90.0,"z":0.0}},{"classname":"light","origin":{"x":-9360.0,"y":4554.6,"z":801.0}},{"classname":"light","origin":{"x":-9360.0,"y":3370.57,"z":801.0}},{"classname":"light","origin":{"x":-9360.0,"y":3962.6,"z":801.0}},{"classname":"light","origin":{"x":-9360.0,"y":2778.57,"z":801.0}},{"classname":"light","origin":{"x":-9360.0,"y":2106.57,"z":473.0}},{"classname":"light","origin":{"x":-9360.0,"y":1658.57,"z":217.0}},{"classname":"light","origin":{"x":-9360.0,"y":1242.57,"z":-15.0}},{"classname":"light","origin":{"x":-9360.0,"y":810.57,"z":-311.0}},{"classname":"light","origin":{"x":-9360.0,"y":185.57,"z":-638.0}},{"classname":"light","origin":{"x":-9360.0,"y":-2432.43,"z":-692.0}},{"classname":"light","origin":{"x":-9360.0,"y":-1840.43,"z":-692.0}},{"classname":"light","origin":{"x":-9360.0,"y":-1248.43,"z":-692.0}},{"classname":"light","origin":{"x":-9360.0,"y":-656.43,"z":-692.0}},{"classname":"light","origin":{"x":-9360.0,"y":-3024.43,"z":-692.0}},{"classname":"trigger_push","origin":{"x":-9360.0,"y":4050.6,"z":721.0}},{"classname":"trigger_teleport","origin":{"x":-9360.0,"y":1442.57,"z":-51.0}},{"classname":"trigger_teleport","origin":{"x":-9360.0,"y":3907.6,"z":-158.0}},{"classname":"trigger_teleport","origin":{"x":-9360.0,"y":1085.57,"z":-898.5}},{"classname":"trigger_teleport","origin":{"x":-9360.0,"y":-1828.43,"z":-1664.0}},{"classname":"light","origin":{"x":-9360.0,"y":-5725.43,"z":472.861}},{"classname":"light","origin":{"x":-9360.0,"y":-5277.43,"z":216.861}},{"classname":"light","origin":{"x":-9360.0,"y":-4861.43,"z":-15.139}},{"classname":"light","origin":{"x":-9360.0,"y":-4429.43,"z":-311.139}},{"classname":"light","origin":{"x":-9360.0,"y":-3804.43,"z":-638.14}},{"classname":"point_spotlight","origin":{"x":-8552.0,"y":-3228.43,"z":-1625.0},"angles":{"x":-90.0,"y":0.0,"z":0.0}},{"classname":"light_spot","origin":{"x":-8552.0,"y":-3228.43,"z":-1629.0},"angles":{"x":90.0,"y":90.0,"z":0.0}},{"classname":"point_spotlight","origin":{"x":-10168.0,"y":-3228.43,"z":-1625.0},"angles":{"x":-90.0,"y":0.0,"z":0.0}},{"classname":"light_spot","origin":{"x":-10168.0,"y":-3228.43,"z":-1629.0},"angles":{"x":90.0,"y":90.0,"z":0.0}},{"classname":"point_spotlight","origin":{"x":-10168.0,"y":-2244.43,"z":-1625.0},"angles":{"x":-90.0,"y":0.0,"z":0.0}},{"classname":"light_spot","origin":{"x":-10168.0,"y":-2244.43,"z":-1629.0},"angles":{"x":90.0,"y":90.0,"z":0.0}},{"classname":"point_spotlight","origin":{"x":-8552.0,"y":-2244.43,"z":-1625.0},"angles":{"x":-90.0,"y":0.0,"z":0.0}},{"classname":"light_spot","origin":{"x":-8552.0,"y":-2244.43,"z":-1629.0},"angles":{"x":90.0,"y":90.0,"z":0.0}},{"classname":"point_spotlight","origin":{"x":-10168.0,"y":-1260.43,"z":-1625.0},"angles":{"x":-90.0,"y":0.0,"z":0.0}},{"classname":"light_spot","origin":{"x":-10168.0,"y":-1260.43,"z":-1629.0},"angles":{"x":90.0,"y":90.0,"z":0.0}},{"classname":"point_spotlight","origin":{"x":-8552.0,"y":-1260.43,"z":-1625.0},"angles":{"x":-90.0,"y":0.0,"z":0.0}},{"classname":"light_spot","origin":{"x":-8552.0,"y":-1260.43,"z":-1629.0},"angles":{"x":90.0,"y":90.0,"z":0.0}},{"classname":"point_spotlight","origin":{"x":-8552.0,"y":-276.43,"z":-1625.0},"angles":{"x":-90.0,"y":0.0,"z":0.0}},{"classname":"light_spot","origin":{"x":-8552.0,"y":-276.43,"z":-1629.0},"angles":{"x":90.0,"y":90.0,"z":0.0}},{"classname":"point_spotlight","origin":{"x":-10168.0,"y":-276.43,"z":-1625.0},"angles":{"x":-90.0,"y":0.0,"z":0.0}},{"classname":"light_spot","origin":{"x":-10168.0,"y":-276.43,"z":-1629.0},"angles":{"x":90.0,"y":90.0,"z":0.0}},{"classname":"light","origin":{"x":-9360.0,"y":-6772.43,"z":473.0}},{"classname":"light","origin":{"x":-9360.0,"y":-6180.43,"z":473.0}},{"classname":"point_spotlight","origin":{"x":-10168.0,"y":-7069.43,"z":-119.0},"angles":{"x":-90.0,"y":0.0,"z":0.0}},{"classname":"light_spot","origin":{"x":-10168.0,"y":-7069.43,"z":-123.0},"angles":{"x":90.0,"y":90.0,"z":0.0}},{"classname":"point_spotlight","origin":{"x":-8552.0,"y":-7069.43,"z":-119.0},"angles":{"x":-90.0,"y":0.0,"z":0.0}},{"classname":"light_spot","origin":{"x":-8552.0,"y":-7069.43,"z":-123.0},"angles":{"x":90.0,"y":90.0,"z":0.0}},{"classname":"point_spotlight","origin":{"x":-8552.0,"y":-6085.43,"z":-119.0},"angles":{"x":-90.0,"y":0.0,"z":0.0}},{"classname":"light_spot","origin":{"x":-8552.0,"y":-6085.43,"z":-123.0},"angles":{"x":90.0,"y":90.0,"z":0.0}},{"classname":"point_spotlight","origin":{"x":-10168.0,"y":-6085.43,"z":-119.0},"angles":{"x":-90.0,"y":0.0,"z":0.0}},{"classname":"light_spot","origin":{"x":-10168.0,"y":-6085.43,"z":-123.0},"angles":{"x":90.0,"y":90.0,"z":0.0}},{"classname":"trigger_push","origin":{"x":-9360.0,"y":-1828.43,"z":-964.5}},{"classname":"trigger_teleport","origin":{"x":-9360.0,"y":-6573.43,"z":-158.5}},{"classname":"trigger_teleport","origin":{"x":-9360.0,"y":-7129.43,"z":545.0}},{"classname":"trigger_teleport","origin":{"x":-9360.0,"y":-5061.43,"z":-51.14}},{"classname":"trigger_teleport","origin":{"x":-9360.0,"y":-4704.53,"z":-918.07}},{"classname":"light","origin":{"x":-5168.5,"y":1573.5,"z":-1178.5}},{"classname":"light","origin":{"x":-5168.5,"y":1573.5,"z":-1178.5}},{"classname":"trigger_push","origin":{"x":-4368.5,"y":-274.67,"z":-924.5}},{"classname":"light","origin":{"x":-3568.17,"y":-1709.51,"z":-1178.5}},{"classname":"light","origin":{"x":-3568.17,"y":-1053.51,"z":-1178.5}},{"classname":"light","origin":{"x":-3568.17,"y":-397.51,"z":-1178.5}},{"classname":"light","origin":{"x":-5168.5,"y":-1706.5,"z":-1178.5}},{"classname":"light","origin":{"x":-5168.5,"y":-1050.5,"z":-1178.5}},{"classname":"light","origin":{"x":-5168.5,"y":-2271.5,"z":-454.5}},{"classname":"light","origin":{"x":-3568.17,"y":-2274.51,"z":-454.5}},{"classname":"light","origin":{"x":-5168.5,"y":-2231.5,"z":319.5}},{"classname":"light","origin":{"x":-3568.17,"y":-2234.51,"z":319.5}},{"classname":"light","origin":{"x":-5168.5,"y":-1854.5,"z":1033.5}},{"classname":"light","origin":{"x":-3568.17,"y":-1857.51,"z":1033.5}},{"classname":"light","origin":{"x":-5168.5,"y":-1080.5,"z":1271.5}},{"classname":"light","origin":{"x":-3568.17,"y":-1083.51,"z":1271.5}},{"classname":"light","origin":{"x":-5168.5,"y":-237.5,"z":1261.5}},{"classname":"light","origin":{"x":-3568.17,"y":-240.51,"z":1261.5}},{"classname":"light","origin":{"x":-5168.5,"y":675.5,"z":1211.5}},{"classname":"light","origin":{"x":-3568.17,"y":672.49,"z":1211.5}},{"classname":"light","origin":{"x":-5168.5,"y":1290.5,"z":1211.5}},{"classname":"light","origin":{"x":-3568.17,"y":1287.49,"z":1211.5}},{"classname":"light","origin":{"x":-5168.5,"y":2123.5,"z":1211.5}},{"classname":"light","origin":{"x":-3568.17,"y":2120.49,"z":1211.5}},{"classname":"light","origin":{"x":-3568.17,"y":3172.49,"z":1290.5}},{"classname":"light","origin":{"x":-5168.5,"y":3175.5,"z":1290.5}},{"classname":"light","origin":{"x":-3568.17,"y":4273.5,"z":1032.5}},{"classname":"light","origin":{"x":-5168.5,"y":4276.5,"z":1032.5}},{"classname":"light","origin":{"x":-3568.17,"y":4759.5,"z":288.5}},{"classname":"light","origin":{"x":-5168.5,"y":4762.5,"z":288.5}},{"classname":"light","origin":{"x":-3568.17,"y":4283.5,"z":-425.5}},{"classname":"light","origin":{"x":-5168.5,"y":4286.5,"z":-425.5}},{"classname":"light","origin":{"x":-3568.17,"y":3390.49,"z":-514.5}},{"classname":"light","origin":{"x":-5168.5,"y":3393.5,"z":-514.5}},{"classname":"light","origin":{"x":-3568.17,"y":2785.49,"z":150.5}},{"classname":"light","origin":{"x":-5168.5,"y":2788.5,"z":150.5}},{"classname":"light","origin":{"x":-3568.17,"y":3589.5,"z":368.5}},{"classname":"trigger_teleport","origin":{"x":-4361.5,"y":-576.5,"z":1226.0}},{"classname":"trigger_teleport","origin":{"x":-4368.51,"y":1689.0,"z":1358.5}},{"classname":"trigger_teleport","origin":{"x":-4367.5,"y":3813.0,"z":-520.26}},{"classname":"trigger_teleport","origin":{"x":-4368.5,"y":3106.5,"z":-69.5}},{"classname":"trigger_teleport","origin":{"x":-4366.0,"y":3373.51,"z":82.74}},{"classname":"trigger_teleport","origin":{"x":-4362.03,"y":-927.5,"z":974.0}},{"classname":"light","origin":{"x":528.0,"y":2406.0,"z":-743.0}},{"classname":"light","origin":{"x":528.0,"y":1614.0,"z":-819.0}},{"classname":"light","origin":{"x":528.0,"y":1604.0,"z":-211.0}},{"classname":"light","origin":{"x":528.0,"y":2396.0,"z":-135.0}},{"classname":"light","origin":{"x":528.0,"y":632.0,"z":-830.0}},{"classname":"light","origin":{"x":528.0,"y":622.0,"z":-222.0}},{"classname":"light","origin":{"x":528.0,"y":-246.0,"z":-526.0}},{"classname":"light","origin":{"x":528.0,"y":-901.0,"z":-606.0}},{"classname":"light","origin":{"x":528.0,"y":-1739.0,"z":-905.0}},{"classname":"light","origin":{"x":528.0,"y":-1749.0,"z":-297.0}},{"classname":"light","origin":{"x":528.0,"y":-1002.0,"z":-2242.0}},{"classname":"light","origin":{"x":528.0,"y":-1012.0,"z":-1634.0}},{"classname":"light","origin":{"x":528.0,"y":267.0,"z":-2413.0}},{"classname":"light","origin":{"x":528.0,"y":257.0,"z":-1805.0}},{"classname":"light","origin":{"x":528.0,"y":1416.0,"z":-2464.0}},{"classname":"light","origin":{"x":528.0,"y":1406.0,"z":-1856.0}},{"classname":"light","origin":{"x":528.0,"y":2856.0,"z":-2481.0}},{"classname":"light","origin":{"x":528.0,"y":2846.0,"z":-1873.0}},{"classname":"trigger_teleport","origin":{"x":531.5,"y":-562.0,"z":-691.5}},{"classname":"trigger_teleport","origin":{"x":526.0,"y":1020.0,"z":-3047.5}},{"classname":"trigger_teleport","origin":{"x":528.0,"y":3153.0,"z":-51.2}},{"classname":"trigger_teleport","origin":{"x":531.0,"y":2773.0,"z":643.66}},{"classname":"trigger_teleport","origin":{"x":528.0,"y":1626.0,"z":-1258.5}},{"classname":"trigger_push","origin":{"x":528.41,"y":2058.9,"z":-2196.1}},{"classname":"trigger_teleport","origin":{"x":528.5,"y":2028.5,"z":427.69}},{"classname":"trigger_teleport","origin":{"x":528.0,"y":3842.0,"z":-60.0}},{"classname":"light","origin":{"x":8776.0,"y":2809.0,"z":-376.0}},{"classname":"trigger_teleport","origin":{"x":9480.0,"y":753.0,"z":-3111.5}},{"classname":"trigger_teleport","origin":{"x":9488.0,"y":321.0,"z":-2031.5}},{"classname":"trigger_teleport","origin":{"x":9488.0,"y":2693.0,"z":-1012.0}},{"classname":"trigger_teleport","origin":{"x":9488.0,"y":17.0,"z":-47.5}},{"classname":"trigger_teleport","origin":{"x":9488.0,"y":881.0,"z":-1735.5}},{"classname":"trigger_push","origin":{"x":9488.0,"y":3277.0,"z":1140.0}},{"classname":"trigger_multiple","origin":{"x":192.0,"y":-1454.5,"z":0.0}},{"classname":"info_player_counterterrorist","origin":{"x":-10386.4,"y":7919.2,"z":186.542},"angles":{"x":0.0,"y":0.0,"z":0.0}},{"targetname":"desty_spawn","classname":"info_teleport_destination","origin":{"x":-10660.0,"y":7612.0,"z":-130.0},"angles":{"x":0.0,"y":0.0,"z":0.0}},{"classname":"info_player_counterterrorist","origin":{"x":-10452.7,"y":7914.7,"z":186.619},"angles":{"x":0.0,"y":0.0,"z":0.0}},{"classname":"info_player_counterterrorist","origin":{"x":-10528.1,"y":7914.6,"z":186.619},"angles":{"x":0.0,"y":0.0,"z":0.0}},{"classname":"info_player_counterterrorist","origin":{"x":-10604.6,"y":7914.6,"z":186.619},"angles":{"x":0.0,"y":0.0,"z":0.0}},{"classname":"info_player_counterterrorist","origin":{"x":-10680.3,"y":7914.4,"z":186.619},"angles":{"x":0.0,"y":0.0,"z":0.0}},{"classname":"info_player_counterterrorist","origin":{"x":-10757.6,"y":7914.6,"z":186.619},"angles":{"x":0.0,"y":0.0,"z":0.0}},{"classname":"trigger_teleport","origin":{"x":-10564.5,"y":7595.65,"z":224.5}},{"classname":"point_spotlight","origin":{"x":-2697.0,"y":-6233.0,"z":2656.0},"angles":{"x":-90.0,"y":0.0,"z":0.0}},{"classname":"light_spot","origin":{"x":-2697.0,"y":-6233.0,"z":2652.0},"angles":{"x":90.0,"y":90.0,"z":0.0}},{"classname":"point_spotlight","origin":{"x":-1939.0,"y":-6233.0,"z":2656.0},"angles":{"x":-90.0,"y":0.0,"z":0.0}},{"classname":"light_spot","origin":{"x":-1939.0,"y":-6233.0,"z":2652.0},"angles":{"x":90.0,"y":90.0,"z":0.0}},{"classname":"point_spotlight","origin":{"x":-2310.0,"y":-6233.0,"z":2656.0},"angles":{"x":-90.0,"y":0.0,"z":0.0}},{"classname":"light_spot","origin":{"x":-2310.0,"y":-6233.0,"z":2652.0},"angles":{"x":90.0,"y":90.0,"z":0.0}},{"classname":"point_spotlight","origin":{"x":-932.0,"y":-6233.0,"z":2326.0},"angles":{"x":-90.0,"y":0.0,"z":0.0}},{"classname":"light_spot","origin":{"x":-932.0,"y":-6233.0,"z":2322.0},"angles":{"x":90.0,"y":90.0,"z":0.0}},{"classname":"point_spotlight","origin":{"x":-67.0,"y":-5681.0,"z":2326.0},"angles":{"x":-90.0,"y":0.0,"z":0.0}},{"classname":"light_spot","origin":{"x":-67.0,"y":-5681.0,"z":2322.0},"angles":{"x":90.0,"y":90.0,"z":0.0}},{"classname":"point_spotlight","origin":{"x":-67.0,"y":-6785.0,"z":2326.0},"angles":{"x":-90.0,"y":0.0,"z":0.0}},{"classname":"light_spot","origin":{"x":-67.0,"y":-6785.0,"z":2322.0},"angles":{"x":90.0,"y":90.0,"z":0.0}},{"classname":"point_spotlight","origin":{"x":957.0,"y":-6233.0,"z":2326.0},"angles":{"x":-90.0,"y":0.0,"z":0.0}},{"classname":"light_spot","origin":{"x":957.0,"y":-6233.0,"z":2322.0},"angles":{"x":90.0,"y":90.0,"z":0.0}},{"classname":"point_spotlight","origin":{"x":1854.0,"y":-6233.0,"z":2326.0},"angles":{"x":-90.0,"y":0.0,"z":0.0}},{"classname":"light_spot","origin":{"x":1854.0,"y":-6233.0,"z":2322.0},"angles":{"x":90.0,"y":90.0,"z":0.0}},{"classname":"point_spotlight","origin":{"x":2751.0,"y":-6233.0,"z":2326.0},"angles":{"x":-90.0,"y":0.0,"z":0.0}},{"classname":"light_spot","origin":{"x":2751.0,"y":-6233.0,"z":2322.0},"angles":{"x":90.0,"y":90.0,"z":0.0}},{"classname":"point_spotlight","origin":{"x":4781.0,"y":-6785.0,"z":1782.0},"angles":{"x":-90.0,"y":0.0,"z":0.0}},{"classname":"light_spot","origin":{"x":4781.0,"y":-6785.0,"z":1778.0},"angles":{"x":90.0,"y":90.0,"z":0.0}},{"classname":"point_spotlight","origin":{"x":4781.0,"y":-5681.0,"z":1782.0},"angles":{"x":-90.0,"y":0.0,"z":0.0}},{"classname":"light_spot","origin":{"x":4781.0,"y":-5681.0,"z":1778.0},"angles":{"x":90.0,"y":90.0,"z":0.0}},{"classname":"point_spotlight","origin":{"x":6079.0,"y":-6785.0,"z":1782.0},"angles":{"x":-90.0,"y":0.0,"z":0.0}},{"classname":"light_spot","origin":{"x":6079.0,"y":-6785.0,"z":1778.0},"angles":{"x":90.0,"y":90.0,"z":0.0}},{"classname":"point_spotlight","origin":{"x":6079.0,"y":-5681.0,"z":1782.0},"angles":{"x":-90.0,"y":0.0,"z":0.0}},{"classname":"light_spot","origin":{"x":6079.0,"y":-5681.0,"z":1778.0},"angles":{"x":90.0,"y":90.0,"z":0.0}},{"classname":"point_spotlight","origin":{"x":7377.0,"y":-6785.0,"z":1968.0},"angles":{"x":-90.0,"y":0.0,"z":0.0}},{"classname":"light_spot","origin":{"x":7377.0,"y":-6785.0,"z":1964.0},"angles":{"x":90.0,"y":90.0,"z":0.0}},{"classname":"point_spotlight","origin":{"x":8675.0,"y":-6785.0,"z":1968.0},"angles":{"x":-90.0,"y":0.0,"z":0.0}},{"classname":"light_spot","origin":{"x":8675.0,"y":-6785.0,"z":1964.0},"angles":{"x":90.0,"y":90.0,"z":0.0}},{"classname":"point_spotlight","origin":{"x":8675.0,"y":-5681.0,"z":1968.0},"angles":{"x":-90.0,"y":0.0,"z":0.0}},{"classname":"light_spot","origin":{"x":8675.0,"y":-5681.0,"z":1964.0},"angles":{"x":90.0,"y":90.0,"z":0.0}},{"classname":"point_spotlight","origin":{"x":7377.0,"y":-5681.0,"z":1968.0},"angles":{"x":-90.0,"y":0.0,"z":0.0}},{"classname":"light_spot","origin":{"x":7377.0,"y":-5681.0,"z":1964.0},"angles":{"x":90.0,"y":90.0,"z":0.0}},{"classname":"point_spotlight","origin":{"x":11293.0,"y":-5681.0,"z":626.0},"angles":{"x":-90.0,"y":0.0,"z":0.0}},{"classname":"light_spot","origin":{"x":11293.0,"y":-5681.0,"z":622.0},"angles":{"x":90.0,"y":90.0,"z":0.0}},{"classname":"point_spotlight","origin":{"x":11293.0,"y":-6785.0,"z":626.0},"angles":{"x":-90.0,"y":0.0,"z":0.0}},{"classname":"light_spot","origin":{"x":11293.0,"y":-6785.0,"z":622.0},"angles":{"x":90.0,"y":90.0,"z":0.0}},{"classname":"point_spotlight","origin":{"x":7684.0,"y":-5681.0,"z":624.0},"angles":{"x":-90.0,"y":0.0,"z":0.0}},{"classname":"light_spot","origin":{"x":7684.0,"y":-5681.0,"z":620.0},"angles":{"x":90.0,"y":90.0,"z":0.0}},{"classname":"point_spotlight","origin":{"x":7684.0,"y":-6785.0,"z":624.0},"angles":{"x":-90.0,"y":0.0,"z":0.0}},{"classname":"light_spot","origin":{"x":7684.0,"y":-6785.0,"z":620.0},"angles":{"x":90.0,"y":90.0,"z":0.0}},{"classname":"point_spotlight","origin":{"x":4237.0,"y":-5681.0,"z":624.0},"angles":{"x":-90.0,"y":0.0,"z":0.0}},{"classname":"light_spot","origin":{"x":4237.0,"y":-5681.0,"z":620.0},"angles":{"x":90.0,"y":90.0,"z":0.0}},{"classname":"point_spotlight","origin":{"x":4237.0,"y":-6785.0,"z":624.0},"angles":{"x":-90.0,"y":0.0,"z":0.0}},{"classname":"light_spot","origin":{"x":4237.0,"y":-6785.0,"z":620.0},"angles":{"x":90.0,"y":90.0,"z":0.0}},{"classname":"point_spotlight","origin":{"x":5983.0,"y":-6233.0,"z":624.0},"angles":{"x":-90.0,"y":0.0,"z":0.0}},{"classname":"light_spot","origin":{"x":5983.0,"y":-6233.0,"z":620.0},"angles":{"x":90.0,"y":90.0,"z":0.0}},{"classname":"point_spotlight","origin":{"x":4038.0,"y":-5681.0,"z":-536.0},"angles":{"x":-90.0,"y":0.0,"z":0.0}},{"classname":"light_spot","origin":{"x":4038.0,"y":-5681.0,"z":-540.0},"angles":{"x":90.0,"y":90.0,"z":0.0}},{"classname":"point_spotlight","origin":{"x":4038.0,"y":-6785.0,"z":-536.0},"angles":{"x":-90.0,"y":0.0,"z":0.0}},{"classname":"light_spot","origin":{"x":4038.0,"y":-6785.0,"z":-540.0},"angles":{"x":90.0,"y":90.0,"z":0.0}},{"classname":"point_spotlight","origin":{"x":5284.0,"y":-5681.0,"z":-536.0},"angles":{"x":-90.0,"y":0.0,"z":0.0}},{"classname":"light_spot","origin":{"x":5284.0,"y":-5681.0,"z":-540.0},"angles":{"x":90.0,"y":90.0,"z":0.0}},{"classname":"point_spotlight","origin":{"x":5284.0,"y":-6785.0,"z":-536.0},"angles":{"x":-90.0,"y":0.0,"z":0.0}},{"classname":"light_spot","origin":{"x":5284.0,"y":-6785.0,"z":-540.0},"angles":{"x":90.0,"y":90.0,"z":0.0}},{"classname":"point_spotlight","origin":{"x":7133.0,"y":-6233.0,"z":-3104.0},"angles":{"x":-90.0,"y":0.0,"z":0.0}},{"classname":"light_spot","origin":{"x":7133.0,"y":-6233.0,"z":-3108.0},"angles":{"x":90.0,"y":90.0,"z":0.0}},{"classname":"point_spotlight","origin":{"x":8277.0,"y":-6233.0,"z":-3104.0},"angles":{"x":-90.0,"y":0.0,"z":0.0}},{"classname":"light_spot","origin":{"x":8277.0,"y":-6233.0,"z":-3108.0},"angles":{"x":90.0,"y":90.0,"z":0.0}},{"classname":"point_spotlight","origin":{"x":9421.0,"y":-6233.0,"z":-3104.0},"angles":{"x":-90.0,"y":0.0,"z":0.0}},{"classname":"light_spot","origin":{"x":9421.0,"y":-6233.0,"z":-3108.0},"angles":{"x":90.0,"y":90.0,"z":0.0}},{"classname":"point_spotlight","origin":{"x":10804.0,"y":-6233.0,"z":-3104.0},"angles":{"x":-90.0,"y":0.0,"z":0.0}},{"classname":"light_spot","origin":{"x":10804.0,"y":-6233.0,"z":-3108.0},"angles":{"x":90.0,"y":90.0,"z":0.0}},{"classname":"point_spotlight","origin":{"x":10621.0,"y":-4633.0,"z":-3104.0},"angles":{"x":-90.0,"y":0.0,"z":0.0}},{"classname":"light_spot","origin":{"x":10621.0,"y":-4633.0,"z":-3108.0},"angles":{"x":90.0,"y":90.0,"z":0.0}},{"classname":"point_spotlight","origin":{"x":10621.0,"y":-7833.0,"z":-3104.0},"angles":{"x":-90.0,"y":0.0,"z":0.0}},{"classname":"light_spot","origin":{"x":10621.0,"y":-7833.0,"z":-3108.0},"angles":{"x":90.0,"y":90.0,"z":0.0}},{"classname":"point_spotlight","origin":{"x":9917.0,"y":-8404.0,"z":-3104.0},"angles":{"x":-90.0,"y":0.0,"z":0.0}},{"classname":"light_spot","origin":{"x":9917.0,"y":-8404.0,"z":-3108.0},"angles":{"x":90.0,"y":90.0,"z":0.0}},{"classname":"point_spotlight","origin":{"x":9918.0,"y":-4062.0,"z":-3104.0},"angles":{"x":-90.0,"y":0.0,"z":0.0}},{"classname":"light_spot","origin":{"x":9918.0,"y":-4062.0,"z":-3108.0},"angles":{"x":90.0,"y":90.0,"z":0.0}},{"classname":"point_spotlight","origin":{"x":7500.0,"y":-4069.0,"z":-3104.0},"angles":{"x":-90.0,"y":0.0,"z":0.0}},{"classname":"light_spot","origin":{"x":7500.0,"y":-4069.0,"z":-3108.0},"angles":{"x":90.0,"y":90.0,"z":0.0}},{"classname":"point_spotlight","origin":{"x":7500.0,"y":-8397.0,"z":-3104.0},"angles":{"x":-90.0,"y":0.0,"z":0.0}},{"classname":"light_spot","origin":{"x":7500.0,"y":-8397.0,"z":-3108.0},"angles":{"x":90.0,"y":90.0,"z":0.0}},{"classname":"func_conveyor"},{"targetname":"desty_stage5","classname":"info_teleport_destination","origin":{"x":-3525.0,"y":-6233.0,"z":2772.0},"angles":{"x":0.0,"y":0.0,"z":0.0}},{"classname":"light","origin":{"x":8733.0,"y":-7119.0,"z":2180.0}},{"classname":"light","origin":{"x":8317.0,"y":-7119.0,"z":2180.0}},{"classname":"light","origin":{"x":7901.0,"y":-7119.0,"z":2180.0}},{"classname":"light","origin":{"x":7485.0,"y":-7119.0,"z":2180.0}},{"classname":"light","origin":{"x":7069.0,"y":-7119.0,"z":2180.0}},{"classname":"light","origin":{"x":7069.0,"y":-5345.0,"z":2180.0}},{"classname":"light","origin":{"x":8733.0,"y":-5345.0,"z":2180.0}},{"classname":"light","origin":{"x":8317.0,"y":-5345.0,"z":2180.0}},{"classname":"light","origin":{"x":7901.0,"y":-5345.0,"z":2180.0}},{"classname":"light","origin":{"x":7485.0,"y":-5345.0,"z":2180.0}},{"classname":"trigger_teleport","origin":{"x":4365.0,"y":-6233.0,"z":-263.0}},{"classname":"trigger_teleport","origin":{"x":6703.5,"y":-6233.0,"z":-2568.0}},{"classname":"light","origin":{"x":10109.0,"y":-6233.0,"z":2139.0}},{"classname":"light","origin":{"x":11091.0,"y":-6233.0,"z":1296.0}},{"classname":"light","origin":{"x":5663.0,"y":-6665.0,"z":2245.0}},{"classname":"light","origin":{"x":5663.0,"y":-5788.0,"z":2243.0}},{"classname":"light","origin":{"x":1989.0,"y":-6233.0,"z":2836.0}},{"classname":"light","origin":{"x":-243.0,"y":-5841.0,"z":2840.0}},{"classname":"light","origin":{"x":-243.0,"y":-6625.0,"z":2840.0}},{"classname":"light","origin":{"x":-2307.0,"y":-6233.0,"z":2860.0}},{"classname":"light","origin":{"x":-1931.0,"y":-6233.0,"z":2860.0}},{"classname":"light","origin":{"x":-3267.0,"y":-6233.0,"z":2936.0}},{"classname":"light","origin":{"x":10053.0,"y":-6230.19,"z":1032.0}},{"classname":"light","origin":{"x":8757.0,"y":-6230.19,"z":1032.0}},{"classname":"light","origin":{"x":9405.0,"y":-6230.19,"z":1032.0}},{"classname":"light","origin":{"x":7742.0,"y":-6233.0,"z":1254.0}},{"classname":"light","origin":{"x":5993.0,"y":-6233.0,"z":1254.0}},{"classname":"light","origin":{"x":4241.0,"y":-6233.0,"z":1254.0}},{"classname":"light","origin":{"x":4169.0,"y":-6233.0,"z":-36.0}},{"classname":"light","origin":{"x":6260.0,"y":-6233.0,"z":-165.0}},{"classname":"light","origin":{"x":7306.0,"y":-6233.0,"z":-1853.0}},{"classname":"light","origin":{"x":7907.0,"y":-6233.0,"z":-2482.0}},{"classname":"light","origin":{"x":9200.0,"y":-6233.0,"z":-2475.0}},{"classname":"light","origin":{"x":10805.0,"y":-6233.0,"z":-2461.0}},{"classname":"light","origin":{"x":10367.0,"y":-4292.0,"z":-2461.0}},{"classname":"light","origin":{"x":7755.0,"y":-4083.0,"z":-2461.0}},{"classname":"light","origin":{"x":7745.0,"y":-8390.0,"z":-2461.0}},{"classname":"light","origin":{"x":10417.0,"y":-8181.0,"z":-2461.0}},{"classname":"trigger_teleport","origin":{"x":7320.5,"y":-6227.5,"z":2299.0}},{"classname":"trigger_teleport","origin":{"x":9488.0,"y":1736.0,"z":2196.0}},{"classname":"trigger_teleport","origin":{"x":9488.0,"y":881.0,"z":1832.5}},{"classname":"trigger_teleport","origin":{"x":9488.0,"y":2780.5,"z":976.5}},{"classname":"trigger_teleport","origin":{"x":9488.0,"y":-579.0,"z":1520.5}},{"classname":"trigger_teleport","origin":{"x":9488.0,"y":-1935.0,"z":1520.5}},{"classname":"trigger_teleport","origin":{"x":9488.0,"y":-1935.0,"z":1520.5}},{"index":0,"clusters":[1548,1549,1550,1556,1559,1560,1561,1581,1582,1583,1586,1587,1590,1591,1594,1599,1600,1601,1602,1603,1604,1605,1606,1609,1610,1611,1612,1613,1614,1615,1616,1617,1618,1619,1620,1621,1622,1626,1628,1629,1630,1631,1633,1634,1635,1636,1637,1638,1640,1641,1642,1643,1644,1645,1646,1647,1648,1649,1650,1651,1652,1656,1657,1658,1659,1660,1661,1662,1663,1664,1665,1666,1667,1672,1675,1676,1677,1679,1680,1681,1683,1685,1686,1687,1689,1691,1692,1707,1709,1710,1711,1712,1713,1714,1715,1716,1717,1718,1719,1720,1721,1722,1723,1724,1725,1726,1727,1728,1729,1730,1731,1734,1735,1738,1739,1740,1741,1743,1747,1748,1749],"classname":"displacement"}]}